{
  "country": "France",
  "flag": "🇫🇷",
  "code": "FR",
  "continent": "Europe",
  "categories": {
    "secular": {
      "count": 39,
      "artists": [
        {
          "name": "Air",
          "channel": {
            "id": "UCjXmNnJm9jwtGg094LRoFOw",
            "name": "AIRfrenchbandofficial",
            "image": "https://yt3.googleusercontent.com/l_hyqG0yfDnYlKh7s1SoJTUvgpNorSgklT1HALrlfpPA3wGxR4PTA7NJpit6iO8HbpLIRy6BxQ=s88-c-k-c0x00ffffff-no-rj-mo",
            "subscribers": 183000,
            "verified": true
          },
          "topSongs": [
            {
              "videoId": "2ec9Dk8x_UE",
              "title": "AIR - Bintang (Official Music Video)",
              "views": 3524029,
              "duration": "3:34",
              "thumbnail": "https://i.ytimg.com/vi/2ec9Dk8x_UE/hq720.jpg"
            },
            {
              "videoId": "TamDOXponnM",
              "title": "YEJI \"Air\" M/V",
              "views": 20967522,
              "duration": "3:19",
              "thumbnail": "https://i.ytimg.com/vi/TamDOXponnM/hq720.jpg"
            },
            {
              "videoId": "idleF6gvhx0",
              "title": "The Best Of Air  - Air  Greatest Hits Full Album",
              "views": 108775,
              "duration": "1:11:03",
              "thumbnail": "https://i.ytimg.com/vi/idleF6gvhx0/hqdefault.jpg"
            },
            {
              "videoId": "uQauaVbPEAA",
              "title": "AIR play \"Moon Safari\" - Royal Albert Hall - ARTE Concert",
              "views": 1988622,
              "duration": "1:32:09",
              "thumbnail": "https://i.ytimg.com/vi/uQauaVbPEAA/hq720.jpg"
            },
            {
              "videoId": "jjuorGiEUS4",
              "title": "Air: Tiny Desk Concert",
              "views": 919415,
              "duration": "17:01",
              "thumbnail": "https://i.ytimg.com/vi/jjuorGiEUS4/hq720.jpg"
            }
          ],
          "songCount": 5
        },
        {
          "name": "Aya Nakamura",
          "channel": {
            "id": "UC-69vhXlCa3XHbF8JHCQHfg",
            "name": "Aya Nakamura",
            "image": "https://yt3.googleusercontent.com/7rNTZjBuDujyCK1W64qAnDeiBroNMguV-kfYqUhayUDnQkMCwRqT-gJJ-KHtKMEd3JWx0fxhHQ=s88-c-k-c0x00ffffff-no-rj-mo",
            "subscribers": 8369999.999999999,
            "verified": true
          },
          "topSongs": [
            {
              "videoId": "EkGiGf8utCM",
              "title": "Aya Nakamura - Copines (Clip officiel)",
              "views": 691096973,
              "duration": "2:58",
              "thumbnail": "https://i.ytimg.com/vi/EkGiGf8utCM/hq720.jpg"
            },
            {
              "videoId": "hkHLYLI-0rw",
              "title": "Aya Nakamura - Copines (Lyrics)",
              "views": 11120506,
              "duration": "2:57",
              "thumbnail": "https://i.ytimg.com/vi/hkHLYLI-0rw/hqdefault.jpg"
            },
            {
              "videoId": "iPGgnzc34tY",
              "title": "Aya Nakamura - Djadja (Clip officiel)",
              "views": 1046559272,
              "duration": "2:55",
              "thumbnail": "https://i.ytimg.com/vi/iPGgnzc34tY/hq720.jpg"
            },
            {
              "videoId": "_bPa-VG0AWo",
              "title": "Aya Nakamura - Pookie (Clip officiel)",
              "views": 392432481,
              "duration": "3:03",
              "thumbnail": "https://i.ytimg.com/vi/_bPa-VG0AWo/hq720.jpg"
            },
            {
              "videoId": "prd-oyaxhCs",
              "title": "Aya Nakamura & Joé Dwèt Filé - Baddies (Clip officiel)",
              "views": 39872831,
              "duration": "3:37",
              "thumbnail": "https://i.ytimg.com/vi/prd-oyaxhCs/hq720.jpg"
            }
          ],
          "songCount": 5
        },
        {
          "name": "Booba",
          "channel": {
            "id": "UCKS1HX4moHCcDBZnM9k4giw",
            "name": "Booba – Cartoon for Kids",
            "image": "https://yt3.ggpht.com/9ZcNDnYOkeop1HAs5YoOJlSN_NENgKemTnIFUi5mPPwtnvdSCRJRrnYZXAfbPAg-Dmxe0ambqg=s88-c-k-c0x00ffffff-no-rj-mo",
            "subscribers": 6040000,
            "verified": true
          },
          "topSongs": [
            {
              "videoId": "NMoZWfArYw8",
              "title": "Booba - Dracula Castle Night 🦇 Cartoon for kids",
              "views": 24301,
              "duration": "1:03:48",
              "thumbnail": "https://i.ytimg.com/vi/NMoZWfArYw8/hq720_custom_1.jpg"
            },
            {
              "videoId": "-ZkHt5MENLk",
              "title": "Booba - Danger Zone Rules ⚠️ Cartoon for kids",
              "views": 246743,
              "duration": "1:32:37",
              "thumbnail": "https://i.ytimg.com/vi/-ZkHt5MENLk/hq720.jpg"
            },
            {
              "videoId": "ZM7I9oSDleo",
              "title": "Booba - Lost Toy Adventure 🧸 Cartoon for kids",
              "views": 56474,
              "duration": "1:02:59",
              "thumbnail": "https://i.ytimg.com/vi/ZM7I9oSDleo/hq720.jpg"
            },
            {
              "videoId": "vLq5oOwV6g0",
              "title": "Booba 🍲 Bon Appetit 🍔🍜🍢🍕 Food episodes compilation - Funny cartoons for kids - Booba ToonsTV",
              "views": 56650454,
              "duration": "58:52",
              "thumbnail": "https://i.ytimg.com/vi/vLq5oOwV6g0/hq720.jpg"
            },
            {
              "videoId": "OFuzIH5fRTU",
              "title": "Booba 👣 Unerwarteter Gast im Kinderzimmer 3 - Lustige Cartoons für Kinder - Booba ToonsTV",
              "views": 58577729,
              "duration": "1:48:05",
              "thumbnail": "https://i.ytimg.com/vi/OFuzIH5fRTU/hq720.jpg"
            }
          ],
          "songCount": 5
        },
        {
          "name": "Charles Aznavour",
          "channel": {
            "id": "UCHgDHM1lmkadG-uYhPfrbdw",
            "name": "Charles Aznavour",
            "image": "https://yt3.ggpht.com/ytc/AIdro_niJWsxuRQ4SrlAsgrQGhJkeFHfdBZ6KnKV_Foqx4vzyw=s88-c-k-c0x00ffffff-no-rj-mo",
            "subscribers": 664000,
            "verified": true
          },
          "topSongs": [
            {
              "videoId": "fVfnEyLOkrM",
              "title": "Charles Aznavour - La bohème (Official Lyrics Video)",
              "views": 84526224,
              "duration": "4:05",
              "thumbnail": "https://i.ytimg.com/vi/fVfnEyLOkrM/hq720.jpg"
            },
            {
              "videoId": "RlB38Rb0Pk8",
              "title": "Vieilles Chansons✨ Charles Aznavour, Joe Dassin, Michel Sardou, Frédéric François, C Jérome,...",
              "views": 2130033,
              "duration": "1:49:55",
              "thumbnail": "https://i.ytimg.com/vi/RlB38Rb0Pk8/hq720.jpg"
            },
            {
              "videoId": "wVkdaVwMYtY",
              "title": "🎶🎶🎶Charles Aznavour, les plus belles chansons d'une légende!🎼🎼🎼",
              "views": 108175,
              "duration": "1:13:58",
              "thumbnail": "https://i.ytimg.com/vi/wVkdaVwMYtY/hq720.jpg"
            },
            {
              "videoId": "13P-FFcT0po",
              "title": "French love Songs ( 1 hour ) - The 30 Most Beautiful French Songs 🎧Charles Aznavour",
              "views": 260022,
              "duration": "1:00:00",
              "thumbnail": "https://i.ytimg.com/vi/13P-FFcT0po/hq720.jpg"
            },
            {
              "videoId": "dbxyKR1P8vA",
              "title": "Charles Aznavour - Hier encore (Audio Officiel)",
              "views": 45108336,
              "duration": "2:23",
              "thumbnail": "https://i.ytimg.com/vi/dbxyKR1P8vA/hq720.jpg"
            }
          ],
          "songCount": 5
        },
        {
          "name": "Christine and the Queens",
          "channel": {
            "id": "UCvDr_Xznwh4gXIy17vVci1w",
            "name": "Christine and the Queens ",
            "image": "https://yt3.googleusercontent.com/1CVObaFjgacixBB6trp_buNGF1Ift58PyUUm0ADbS616ex_Qa_sRPVhaHfZ35qR9hZUAj_24ZQ=s88-c-k-c0x00ffffff-no-rj-mo",
            "subscribers": 426000,
            "verified": true
          },
          "topSongs": [
            {
              "videoId": "rs40yxHjTxQ",
              "title": "Christine and the Queens - Christine (Clip Officiel)",
              "views": 65926031,
              "duration": "3:57",
              "thumbnail": "https://i.ytimg.com/vi/rs40yxHjTxQ/hq720.jpg"
            },
            {
              "videoId": "piYsFZWmM18",
              "title": "Christine and the Queens - Full of life (Lyric Video)",
              "views": 3902499,
              "duration": "4:33",
              "thumbnail": "https://i.ytimg.com/vi/piYsFZWmM18/hq720.jpg"
            },
            {
              "videoId": "uNGguudoLVs",
              "title": "Christine and the Queens - People, I've been sad | A COLORS SHOW",
              "views": 5809900,
              "duration": "4:26",
              "thumbnail": "https://i.ytimg.com/vi/uNGguudoLVs/hq720.jpg"
            },
            {
              "videoId": "PPjazi4mQSQ",
              "title": "Christine and the Queens - Paradis Perdus (Clip Officiel)",
              "views": 20739085,
              "duration": "3:39",
              "thumbnail": "https://i.ytimg.com/vi/PPjazi4mQSQ/hq720.jpg"
            },
            {
              "videoId": "v8eulIH7tU0",
              "title": "Christine and the Queens - 5 dollars (Official Music Video)",
              "views": 7490823,
              "duration": "3:31",
              "thumbnail": "https://i.ytimg.com/vi/v8eulIH7tU0/hq720.jpg"
            }
          ],
          "songCount": 5
        },
        {
          "name": "Clara Luciani",
          "channel": {
            "id": "UCfEE7VQC9xLMzNssS7y3APA",
            "name": "Clara Luciani",
            "image": "https://yt3.googleusercontent.com/5wlw-hs8UNbjX2YpnQKGyy8eTsCrOa0fHz834rlnByQUsLxQdJ18D7Vz4F2whzKH9MnyiwCb=s88-c-k-c0x00ffffff-no-rj-mo",
            "subscribers": 296000,
            "verified": true
          },
          "topSongs": [
            {
              "videoId": "85m-Qgo9_nE",
              "title": "Clara Luciani - La grenade (Clip officiel)",
              "views": 89232408,
              "duration": "3:15",
              "thumbnail": "https://i.ytimg.com/vi/85m-Qgo9_nE/hq720.jpg"
            },
            {
              "videoId": "uWH00ehhLP8",
              "title": "Clara Luciani - Respire encore (Clip Officiel)",
              "views": 33925538,
              "duration": "3:49",
              "thumbnail": "https://i.ytimg.com/vi/uWH00ehhLP8/hq720.jpg"
            },
            {
              "videoId": "c0fV4w-wLOU",
              "title": "Clara Luciani - Le reste (Clip Officiel)",
              "views": 27167409,
              "duration": "4:08",
              "thumbnail": "https://i.ytimg.com/vi/c0fV4w-wLOU/hq720.jpg"
            },
            {
              "videoId": "VqsU_4KOEA8",
              "title": "Clara Luciani - Amour toujours (Clip officiel)",
              "views": 9358889,
              "duration": "4:06",
              "thumbnail": "https://i.ytimg.com/vi/VqsU_4KOEA8/hq720.jpg"
            },
            {
              "videoId": "A0hRkq4YT1o",
              "title": "Clara Luciani - Tout pour moi",
              "views": 3407787,
              "duration": "3:40",
              "thumbnail": "https://i.ytimg.com/vi/A0hRkq4YT1o/hq720.jpg"
            }
          ],
          "songCount": 5
        },
        {
          "name": "Dadju",
          "channel": {
            "id": "UC8HMvOLE0etpO_eVjJ98bHA",
            "name": "DADJU",
            "image": "https://yt3.googleusercontent.com/5QrcQCkzITdMsS_DspPUactbVY4zOipPffI4G12AK6fQt72DIS2UkdIYh5eK3pOfhtaM6eGIvQ=s88-c-k-c0x00ffffff-no-rj-mo",
            "subscribers": 7890000,
            "verified": true
          },
          "topSongs": [
            {
              "videoId": "254EHfv9RvM",
              "title": "DADJU -  Jaloux (Clip Officiel)",
              "views": 376065419,
              "duration": "3:53",
              "thumbnail": "https://i.ytimg.com/vi/254EHfv9RvM/hq720.jpg"
            },
            {
              "videoId": "tVKaN_H35xs",
              "title": "DADJU - Reine (Clip Officiel)",
              "views": 430594677,
              "duration": "3:19",
              "thumbnail": "https://i.ytimg.com/vi/tVKaN_H35xs/hq720.jpg"
            },
            {
              "videoId": "ozthKn07Ei4",
              "title": "Dadju & Tayc - I love you (Clip officiel)",
              "views": 142118950,
              "duration": "3:21",
              "thumbnail": "https://i.ytimg.com/vi/ozthKn07Ei4/hq720.jpg"
            },
            {
              "videoId": "xO2y82caN4U",
              "title": "MHD - Bébé (feat. Dadju)",
              "views": 213730483,
              "duration": "4:21",
              "thumbnail": "https://i.ytimg.com/vi/xO2y82caN4U/hq720.jpg"
            },
            {
              "videoId": "mmc2sCXrTws",
              "title": "DADJU, ANITTA - Mon soleil (Official video)",
              "views": 125044378,
              "duration": "3:12",
              "thumbnail": "https://i.ytimg.com/vi/mmc2sCXrTws/hq720.jpg"
            }
          ],
          "songCount": 5
        },
        {
          "name": "Daft Punk",
          "channel": {
            "id": "UC_kRDKYrUlrbtrSiyu5Tflg",
            "name": "Daft Punk",
            "image": "https://yt3.googleusercontent.com/XPIjND5mm2nuSIJ6uQyIWLCawnIYSVm6QS0GEN_UNuPLRD5EFa6yCkYrcyLpl3TFuBo6AZynsA=s88-c-k-c0x00ffffff-no-rj-mo",
            "subscribers": 7100000,
            "verified": true
          },
          "topSongs": [
            {
              "videoId": "a5uQMwRMHcs",
              "title": "Daft Punk - Instant Crush (Official Video) ft. Julian Casablancas",
              "views": 864637718,
              "duration": "5:40",
              "thumbnail": "https://i.ytimg.com/vi/a5uQMwRMHcs/hq720.jpg"
            },
            {
              "videoId": "sOS9aOIXPEk",
              "title": "Daft Punk - Something About Us (Official Video)",
              "views": 106954688,
              "duration": "3:49",
              "thumbnail": "https://i.ytimg.com/vi/sOS9aOIXPEk/hq720.jpg"
            },
            {
              "videoId": "gAjR4_CbPpQ",
              "title": "Daft Punk - Harder, Better, Faster, Stronger (Official Video)",
              "views": 159806322,
              "duration": "3:43",
              "thumbnail": "https://i.ytimg.com/vi/gAjR4_CbPpQ/hq720.jpg"
            },
            {
              "videoId": "VeauURD-qLk",
              "title": "D.a.f.t P.u.n.k Greatest Hits 🔥 Best D.a.f.t P.u.n.k Songs & Playlist 🔥 Full Album 2022",
              "views": 849470,
              "duration": "1:11:15",
              "thumbnail": "https://i.ytimg.com/vi/VeauURD-qLk/hq720.jpg"
            },
            {
              "videoId": "K1k35lDpzdw",
              "title": "Digital Galaxy 🍄🤖 | Chillwave, Synthwave, Retro Funk, Disco, Electronic Playlist",
              "views": 1059094,
              "duration": "2:02:24",
              "thumbnail": "https://i.ytimg.com/vi/K1k35lDpzdw/hq720.jpg"
            }
          ],
          "songCount": 5
        },
        {
          "name": "David Guetta",
          "channel": {
            "id": "UC1l7wYrva1qCH-wgqcHaaRg",
            "name": "David Guetta",
            "image": "https://yt3.ggpht.com/ytc/AIdro_nVKPoGkfw44ICB715GPlzNDsmqZdlwewB1QGa9K4vD94o=s88-c-k-c0x00ffffff-no-rj-mo",
            "subscribers": 27800000,
            "verified": true
          },
          "topSongs": [
            {
              "videoId": "g7O-7rF0Hqk",
              "title": "David Guetta live @ Tomorrowland 2024",
              "views": 28850590,
              "duration": "1:08:22",
              "thumbnail": "https://i.ytimg.com/vi/g7O-7rF0Hqk/hq720.jpg"
            },
            {
              "videoId": "mN5AZBrVq9I",
              "title": "Jennifer Lopez & David Guetta - Save Me Tonight (DJs From Mars remix) [Visualizer]",
              "views": 51167,
              "duration": "3:05",
              "thumbnail": "https://i.ytimg.com/vi/mN5AZBrVq9I/hq720.jpg"
            },
            {
              "videoId": "90RLzVUuXe4",
              "title": "David Guetta & Bebe Rexha - I'm Good (Blue) [Official Music Video]",
              "views": 388981902,
              "duration": "2:58",
              "thumbnail": "https://i.ytimg.com/vi/90RLzVUuXe4/hq720.jpg"
            },
            {
              "videoId": "cus3nFOjXb0",
              "title": "David Guetta live @ Tomorrowland 2025 | MainStage Closing Set WE1",
              "views": 6579091,
              "duration": "1:14:49",
              "thumbnail": "https://i.ytimg.com/vi/cus3nFOjXb0/hq720.jpg"
            },
            {
              "videoId": "JRfuAukYTKg",
              "title": "David Guetta - Titanium ft. Sia (Official Video)",
              "views": 2151972703,
              "duration": "4:06",
              "thumbnail": "https://i.ytimg.com/vi/JRfuAukYTKg/hqdefault.jpg"
            }
          ],
          "songCount": 5
        },
        {
          "name": "Dj Snake",
          "channel": {
            "id": "UC_x8HoD18XJkILQBreVENUQ",
            "name": "DJ Snake",
            "image": "https://yt3.googleusercontent.com/Py3hu9uTDbSfZjk2eVgjY2b9nB2IC_S7lCO3TGso3V9W7-ZVklzCZhp-D3IOCTQHUs4Pk_hRc6s=s88-c-k-c0x00ffffff-no-rj-mo",
            "subscribers": 25100000,
            "verified": true
          },
          "topSongs": [
            {
              "videoId": "HMUDVMiITOU",
              "title": "DJ Snake, Lil Jon - Turn Down for What",
              "views": 1263657251,
              "duration": "3:37",
              "thumbnail": "https://i.ytimg.com/vi/HMUDVMiITOU/hq720.jpg"
            },
            {
              "videoId": "YqeW9_5kURI",
              "title": "Major Lazer & DJ Snake - Lean On (feat. MØ) [Official 4K Music Video]",
              "views": 3916280131,
              "duration": "2:59",
              "thumbnail": "https://i.ytimg.com/vi/YqeW9_5kURI/hq720.jpg"
            },
            {
              "videoId": "hSq5aGvBJ04",
              "title": "DJ SNAKE LIVE @ ULTRA MIAMI MAIN STAGE 2026",
              "views": 2121107,
              "duration": "59:39",
              "thumbnail": "https://i.ytimg.com/vi/hSq5aGvBJ04/hq720.jpg"
            },
            {
              "videoId": "ixkoVwKQaJg",
              "title": "DJ Snake - Taki Taki ft. Selena Gomez, Ozuna, Cardi B (Official Music Video)",
              "views": 2800486299,
              "duration": "3:52",
              "thumbnail": "https://i.ytimg.com/vi/ixkoVwKQaJg/hq720.jpg"
            },
            {
              "videoId": "IvPT2QuCIOA",
              "title": "DJ Snake - Middle ft. Bipolar Sunshine",
              "views": 408722065,
              "duration": "5:01",
              "thumbnail": "https://i.ytimg.com/vi/IvPT2QuCIOA/hq720.jpg"
            }
          ],
          "songCount": 5
        },
        {
          "name": "Edith Piaf",
          "channel": {
            "id": "UCehQT6NHMZjl0giIfY7f1mw",
            "name": "Edith Piaf Officiel",
            "image": "https://yt3.googleusercontent.com/R7E-Gqh-7Ha6mJpbXsDDsb1Ee_FlnkuBP3xpw2pT95SHLzcA1ZPNucSTJd3dQ1fla0WsdmOYeA=s88-c-k-c0x00ffffff-no-rj-mo",
            "subscribers": 480000,
            "verified": true
          },
          "topSongs": [
            {
              "videoId": "Q3Kvu6Kgp88",
              "title": "Edith Piaf - Non, Je ne regrette rien",
              "views": 119566648,
              "duration": "2:23",
              "thumbnail": "https://i.ytimg.com/vi/Q3Kvu6Kgp88/hqdefault.jpg"
            },
            {
              "videoId": "IxJQ8VKc4k4",
              "title": "The Best of Edith Piaf",
              "views": 8551566,
              "duration": "1:03:56",
              "thumbnail": "https://i.ytimg.com/vi/IxJQ8VKc4k4/hqdefault.jpg"
            },
            {
              "videoId": "FuXJWb9iSI0",
              "title": "The Best of Edith Piaf Medley: Non, je ne regrette rien / La vie en rose / Hymne à l'amour /...",
              "views": 6253381,
              "duration": "1:03:56",
              "thumbnail": "https://i.ytimg.com/vi/FuXJWb9iSI0/hq720.jpg"
            },
            {
              "videoId": "bUKC5RAjUdg",
              "title": "La Vie Parisienne: French Chansons From the 1930s & 40s Edith Piaf, Reinhardt & Grappelli",
              "views": 10654050,
              "duration": "1:04:31",
              "thumbnail": "https://i.ytimg.com/vi/bUKC5RAjUdg/hq720.jpg"
            },
            {
              "videoId": "qPU8mENUBXk",
              "title": "La Vie En Rose",
              "views": 12213572,
              "duration": "3:08",
              "thumbnail": "https://i.ytimg.com/vi/qPU8mENUBXk/hq720.jpg"
            }
          ],
          "songCount": 5
        },
        {
          "name": "Francoise Hardy",
          "channel": {
            "id": "UCsyR7lxM1qrXURI-3QPFt7g",
            "name": "Francoise Hardy",
            "image": "https://yt3.googleusercontent.com/xb8tG6f8fJFKgOlh3gJeVGS4u-2Ikg9qThHwHyAyT5tNoVP02COWX7zj86TkLg-v_fMdzOHY=s88-c-k-c0x00ffffff-no-rj-mo",
            "subscribers": 144000,
            "verified": true
          },
          "topSongs": [
            {
              "videoId": "ITYVXUvMtHI",
              "title": "Françoise Hardy - Le Temps de l'Amour",
              "views": 20063535,
              "duration": "2:26",
              "thumbnail": "https://i.ytimg.com/vi/ITYVXUvMtHI/hq720.jpg"
            },
            {
              "videoId": "m94_C8Z7wLk",
              "title": "Françoise Hardy - Tous les garçons et les filles (Scopitone officiel)",
              "views": 279111,
              "duration": "2:59",
              "thumbnail": "https://i.ytimg.com/vi/m94_C8Z7wLk/hq720.jpg"
            },
            {
              "videoId": "j-kM3NCEBFk",
              "title": "FRANCOISE HARDY 1966",
              "views": 5941,
              "duration": "29:44",
              "thumbnail": "https://i.ytimg.com/vi/j-kM3NCEBFk/hq720.jpg"
            },
            {
              "videoId": "tINyMbNZytI",
              "title": "Comment te dire adieu (Remasterisé en 2016)",
              "views": 9413025,
              "duration": "2:29",
              "thumbnail": "https://i.ytimg.com/vi/tINyMbNZytI/hq720.jpg"
            },
            {
              "videoId": "c1mDUrexTKo",
              "title": "Voilà (Remasterisé en 2016)",
              "views": 2231848,
              "duration": "3:23",
              "thumbnail": "https://i.ytimg.com/vi/c1mDUrexTKo/hq720.jpg"
            }
          ],
          "songCount": 5
        },
        {
          "name": "IAM",
          "channel": {
            "id": "UCi5HyaSoEE4qLzFTQXrUxRQ",
            "name": "IAM",
            "image": "https://yt3.ggpht.com/t2S-DiXGNPS9xREnRPvvJuIIbe55i1M2OjVhMIj2t8Dvaik0YTfKk2JePwIH8dowp0PSnyAKeA=s88-c-k-c0x00ffffff-no-rj-mo",
            "subscribers": 16800,
            "verified": false
          },
          "topSongs": [
            {
              "videoId": "6ZUIwj3FgUY",
              "title": "IVE 아이브 'I AM' MV",
              "views": 384549694,
              "duration": "3:05",
              "thumbnail": "https://i.ytimg.com/vi/6ZUIwj3FgUY/hq720.jpg"
            },
            {
              "videoId": "8QcDZ6mpYVI",
              "title": "IVE - I AM (Lyrics)",
              "views": 1048395,
              "duration": "3:04",
              "thumbnail": "https://i.ytimg.com/vi/8QcDZ6mpYVI/hq720.jpg"
            },
            {
              "videoId": "dGR7smT0fcY",
              "title": "IAM Explained in 4 minutes - Identity & Access Management",
              "views": 7308,
              "duration": "4:11",
              "thumbnail": "https://i.ytimg.com/vi/dGR7smT0fcY/hq720.jpg"
            },
            {
              "videoId": "RzIGRHCPaKs",
              "title": "What is IAM (Identity and Access Management)?",
              "views": 43282,
              "duration": "5:20",
              "thumbnail": "https://i.ytimg.com/vi/RzIGRHCPaKs/hqdefault.jpg"
            },
            {
              "videoId": "cU0JrSAyy7o",
              "title": "[BE ORIGINAL] IVE(아이브) 'I AM' (4K)",
              "views": 33414367,
              "duration": "3:28",
              "thumbnail": "https://i.ytimg.com/vi/cU0JrSAyy7o/hq720.jpg"
            }
          ],
          "songCount": 5
        },
        {
          "name": "Indila",
          "channel": {
            "id": "UCX4EBb-NmxyntI0mQAErHvQ",
            "name": "Indila",
            "image": "https://yt3.ggpht.com/ytc/AIdro_nsreE5NfVUD-yrBAJS_bE4k7vn3U7TZ7bu-zH6D26EzRA=s88-c-k-c0x00ffffff-no-rj-mo",
            "subscribers": 8080000,
            "verified": true
          },
          "topSongs": [
            {
              "videoId": "K5KAc5CoCuk",
              "title": "Indila - Dernière Danse (Clip Officiel)",
              "views": 1422103831,
              "duration": "3:35",
              "thumbnail": "https://i.ytimg.com/vi/K5KAc5CoCuk/hq720.jpg"
            },
            {
              "videoId": "DF3XjEhJ40Y",
              "title": "Indila - Love Story (Official Music Video)",
              "views": 495834322,
              "duration": "4:45",
              "thumbnail": "https://i.ytimg.com/vi/DF3XjEhJ40Y/hq720.jpg"
            },
            {
              "videoId": "vtNJMAyeP0s",
              "title": "Indila - Tourner Dans Le Vide (Official Music Video)",
              "views": 505254018,
              "duration": "4:11",
              "thumbnail": "https://i.ytimg.com/vi/vtNJMAyeP0s/hq720.jpg"
            },
            {
              "videoId": "HLCqZxwB290",
              "title": "Indila - Dernière Danse (Lyrics)",
              "views": 16738636,
              "duration": "3:34",
              "thumbnail": "https://i.ytimg.com/vi/HLCqZxwB290/hq720.jpg"
            },
            {
              "videoId": "m65jhGwtWrg",
              "title": "Indila - S.O.S (Official Music Video)",
              "views": 294338681,
              "duration": "4:48",
              "thumbnail": "https://i.ytimg.com/vi/m65jhGwtWrg/hq720.jpg"
            }
          ],
          "songCount": 5
        },
        {
          "name": "Johnny Hallyday",
          "channel": {
            "id": "UC9wvnHwKWvE_unCTf1eLKHw",
            "name": "Johnny Hallyday Officiel",
            "image": "https://yt3.googleusercontent.com/htZ-cFgTFxvqz5T3gXHDQRNg3UEEKCVEDxrk3Iivpk4Zex36yzk9hBV8qQoH3EDq51upy4lO1g=s88-c-k-c0x00ffffff-no-rj-mo",
            "subscribers": 978000,
            "verified": true
          },
          "topSongs": [
            {
              "videoId": "-TkrMyXYbik",
              "title": "Johnny Hallyday - Je te promets (Clip Officiel Remasterisé)",
              "views": 89153544,
              "duration": "3:26",
              "thumbnail": "https://i.ytimg.com/vi/-TkrMyXYbik/hq720.jpg"
            },
            {
              "videoId": "s3O1Xro7oAI",
              "title": "Johnny Hallyday - Allumer Le Feu (Clip Officiel Remasterisé)",
              "views": 38250357,
              "duration": "4:19",
              "thumbnail": "https://i.ytimg.com/vi/s3O1Xro7oAI/hq720.jpg"
            },
            {
              "videoId": "PfGstMC6neY",
              "title": "Johnny Hallyday - Que je t'aime (Rester Vivant Tour)",
              "views": 8139224,
              "duration": "4:14",
              "thumbnail": "https://i.ytimg.com/vi/PfGstMC6neY/hq720.jpg"
            },
            {
              "videoId": "Xs-_NZ0LhrA",
              "title": "Johnny Hallyday - Vivre Pour Le Meilleur (Clip Officiel Remasterisé)",
              "views": 62649052,
              "duration": "4:32",
              "thumbnail": "https://i.ytimg.com/vi/Xs-_NZ0LhrA/hq720.jpg"
            },
            {
              "videoId": "CobeBZNlR8E",
              "title": "Johnny Hallyday - J'en parlerai au diable (Clip officiel)",
              "views": 32031669,
              "duration": "4:05",
              "thumbnail": "https://i.ytimg.com/vi/CobeBZNlR8E/hqdefault.jpg"
            }
          ],
          "songCount": 5
        },
        {
          "name": "Jul",
          "channel": {
            "id": "UC7ZuMv7r60Cwn7mRNlPC0LA",
            "name": "JuL",
            "image": "https://yt3.googleusercontent.com/fgONEivqt-NErvIT3gnW38PEOh47l1AuNZ7o0fgsVlMvh1U9m9CKb_HgeZHIIoCuE0QjvKFM=s88-c-k-c0x00ffffff-no-rj-mo",
            "subscribers": 1940000,
            "verified": true
          },
          "topSongs": [
            {
              "videoId": "rTWzswSVjbo",
              "title": "Jul - J'oublie tout [Son Officiel]",
              "views": 330489634,
              "duration": "5:17",
              "thumbnail": "https://i.ytimg.com/vi/rTWzswSVjbo/hq720.jpg"
            },
            {
              "videoId": "dgpagYpMFiM",
              "title": "Jul - It's hard to love [Official Music Video 2026]",
              "views": 6052048,
              "duration": "3:09",
              "thumbnail": "https://i.ytimg.com/vi/dgpagYpMFiM/hq720.jpg"
            },
            {
              "videoId": "X8yNru9psQE",
              "title": "JuL - La faille // Clip Officiel // 2023",
              "views": 125113043,
              "duration": "4:59",
              "thumbnail": "https://i.ytimg.com/vi/X8yNru9psQE/hq720.jpg"
            },
            {
              "videoId": "XZIecgNr1uE",
              "title": "Jul \"C'est la cité\" ft Naps #PlanèteRap",
              "views": 21813149,
              "duration": "3:52",
              "thumbnail": "https://i.ytimg.com/vi/XZIecgNr1uE/hq720.jpg"
            },
            {
              "videoId": "q-3qus2pvJM",
              "title": "Jul - Sousou // Clip Officiel // 2020 📀👽💿",
              "views": 153295886,
              "duration": "3:59",
              "thumbnail": "https://i.ytimg.com/vi/q-3qus2pvJM/hq720.jpg"
            }
          ],
          "songCount": 5
        },
        {
          "name": "Justice",
          "channel": {
            "id": "UCQ5Ssrs48yJBfOesfDqXUeA",
            "name": "Justice",
            "image": "https://yt3.googleusercontent.com/G8roUC7oqQ7RDk2Lg5TInN9ZmB2SI6LBOfXHtNYVOhyRbmvsfBWQwQKrZUVwcXyCSd1f0jJrBg=s88-c-k-c0x00ffffff-no-rj-mo",
            "subscribers": 499000,
            "verified": true
          },
          "topSongs": [
            {
              "videoId": "Yt0kHiRsnHA",
              "title": "Justice -  Cross (Full album)",
              "views": 1409527,
              "duration": "48:22",
              "thumbnail": "https://i.ytimg.com/vi/Yt0kHiRsnHA/hq720.jpg"
            },
            {
              "videoId": "E7FU_mqhFGk",
              "title": "Justice – Neverender (Starring Tame Impala) (Official Video)",
              "views": 6232489,
              "duration": "3:20",
              "thumbnail": "https://i.ytimg.com/vi/E7FU_mqhFGk/hq720.jpg"
            },
            {
              "videoId": "49esza4eiK4",
              "title": "Justice - D.A.N.C.E",
              "views": 10170357,
              "duration": "3:07",
              "thumbnail": "https://i.ytimg.com/vi/49esza4eiK4/hqdefault.jpg"
            },
            {
              "videoId": "VKzWLUQizz8",
              "title": "Justice - Genesis - † (Official Audio)",
              "views": 24652544,
              "duration": "3:55",
              "thumbnail": "https://i.ytimg.com/vi/VKzWLUQizz8/hq720.jpg"
            },
            {
              "videoId": "l9uMoTMbyrQ",
              "title": "Justice - Neverender (Starring Tame Impala) (Live at Accor Arena 2024)",
              "views": 1557004,
              "duration": "9:45",
              "thumbnail": "https://i.ytimg.com/vi/l9uMoTMbyrQ/hq720.jpg"
            }
          ],
          "songCount": 5
        },
        {
          "name": "Kendji Girac",
          "channel": {
            "id": "UCgtt_xijZ03e0THlKDvPauw",
            "name": "Kendji Girac",
            "image": "https://yt3.googleusercontent.com/30T0PgEHLZ-DIV8oHUtZWR2RZxFy6CRLhR5Up2_k7jIemrfybPtDmqdHo6uQhBTAh7UTynUINQ=s88-c-k-c0x00ffffff-no-rj-mo",
            "subscribers": 4160000,
            "verified": true
          },
          "topSongs": [
            {
              "videoId": "FndmvPkI1Ms",
              "title": "Kendji Girac - Andalouse (Clip Officiel)",
              "views": 438928245,
              "duration": "3:24",
              "thumbnail": "https://i.ytimg.com/vi/FndmvPkI1Ms/hq720.jpg"
            },
            {
              "videoId": "iToH6GuN2S4",
              "title": "Kendji Girac - Pour oublier",
              "views": 131504178,
              "duration": "3:51",
              "thumbnail": "https://i.ytimg.com/vi/iToH6GuN2S4/hq720.jpg"
            },
            {
              "videoId": "lVxawLsN48s",
              "title": "Kendji Girac - Bebeto (en duo avec Soolking) (Clip officiel)",
              "views": 151232560,
              "duration": "3:26",
              "thumbnail": "https://i.ytimg.com/vi/lVxawLsN48s/hq720.jpg"
            },
            {
              "videoId": "YgP2whwA2Wg",
              "title": "Kendji Girac - Les yeux de la mama",
              "views": 191622770,
              "duration": "3:22",
              "thumbnail": "https://i.ytimg.com/vi/YgP2whwA2Wg/hq720.jpg"
            },
            {
              "videoId": "xwoPXAcrDyI",
              "title": "Kendji Girac - Elle M'a Aimé (Clip Officiel)",
              "views": 108900902,
              "duration": "4:04",
              "thumbnail": "https://i.ytimg.com/vi/xwoPXAcrDyI/hq720.jpg"
            }
          ],
          "songCount": 5
        },
        {
          "name": "Louane",
          "channel": {
            "id": "UCKLI9RZjAOhNwqoJo3sqXUQ",
            "name": "Louane",
            "image": "https://yt3.googleusercontent.com/4n4tWNPTv02Fuh_VLPjzmzLySAdTQ3APnhcblgj5YvqSlYzuilk3qm1wu7qT76Y-jUyJShTyAA=s88-c-k-c0x00ffffff-no-rj-mo",
            "subscribers": 1690000,
            "verified": true
          },
          "topSongs": [
            {
              "videoId": "xyqSAsR_Tms",
              "title": "Louane - On était beau (Clip Officiel)",
              "views": 44780962,
              "duration": "3:23",
              "thumbnail": "https://i.ytimg.com/vi/xyqSAsR_Tms/hq720.jpg"
            },
            {
              "videoId": "yleB8fUXudw",
              "title": "Louane - JOUR 1 (vidéo officielle)",
              "views": 105705546,
              "duration": "3:43",
              "thumbnail": "https://i.ytimg.com/vi/yleB8fUXudw/hq720.jpg"
            },
            {
              "videoId": "yo-CCYzm_SQ",
              "title": "Louane - Si t’étais là",
              "views": 62675289,
              "duration": "3:17",
              "thumbnail": "https://i.ytimg.com/vi/yo-CCYzm_SQ/hq720.jpg"
            },
            {
              "videoId": "sPsCXm14G58",
              "title": "Louane - Donne-moi ton coeur",
              "views": 17971446,
              "duration": "3:10",
              "thumbnail": "https://i.ytimg.com/vi/sPsCXm14G58/hq720.jpg"
            },
            {
              "videoId": "I_dbhHU1CGA",
              "title": "Louane - Jeune (j’ai envie)",
              "views": 37086374,
              "duration": "3:53",
              "thumbnail": "https://i.ytimg.com/vi/I_dbhHU1CGA/hq720.jpg"
            }
          ],
          "songCount": 5
        },
        {
          "name": "MC Solaar",
          "channel": {
            "id": "UCIVFkPnqaOP5eLRgKCEllqA",
            "name": "MC SOLAAR",
            "image": "https://yt3.googleusercontent.com/TS5T7xfM5CLbPk7FmV9aUyKuRjfSXVUeANBrwoakAeQxGCQWLimR1S1dQ7QXns4AmwOEFwLxdnM=s88-c-k-c0x00ffffff-no-rj-mo",
            "subscribers": 111000,
            "verified": true
          },
          "topSongs": [
            {
              "videoId": "P7fMAhlsZBA",
              "title": "MC Solaar Live Symphonic 2022 - Philharmonie de Paris 4K (Hi-Res 48kHz 24Bit)",
              "views": 6663,
              "duration": "1:32:07",
              "thumbnail": "https://i.ytimg.com/vi/P7fMAhlsZBA/hq720.jpg"
            },
            {
              "videoId": "DMDVaaVrAMo",
              "title": "MC Solaar - Obsolète (Clip officiel)",
              "views": 1879596,
              "duration": "3:24",
              "thumbnail": "https://i.ytimg.com/vi/DMDVaaVrAMo/hq720.jpg"
            },
            {
              "videoId": "cn0myHAzJoQ",
              "title": "MC★Solaar & Marie-Flore - Okay (Clip officiel)",
              "views": 1175627,
              "duration": "3:06",
              "thumbnail": "https://i.ytimg.com/vi/cn0myHAzJoQ/hq720.jpg"
            },
            {
              "videoId": "20baKNd9Pug",
              "title": "MC Solaar - Hasta la vista (Clip Officiel HD)",
              "views": 17490836,
              "duration": "3:39",
              "thumbnail": "https://i.ytimg.com/vi/20baKNd9Pug/hq720.jpg"
            },
            {
              "videoId": "IXGrJVxqbmE",
              "title": "Mc Solaar - Inch'Allah (Clip Officiel)",
              "views": 3751361,
              "duration": "3:12",
              "thumbnail": "https://i.ytimg.com/vi/IXGrJVxqbmE/hqdefault.jpg"
            }
          ],
          "songCount": 5
        },
        {
          "name": "MHD",
          "channel": {
            "id": "UCvebOuGWNvuUpZBzpV_Bc9Q",
            "name": "Mhd Officiel",
            "image": "https://yt3.googleusercontent.com/orh7AUBAJpBoSxnDOkgeNOLMlExqtD1evDR84Kw00phP8jPQ2BCs3tFVYAce2XrhUav782cl=s88-c-k-c0x00ffffff-no-rj-mo",
            "subscribers": 5010000,
            "verified": true
          },
          "topSongs": [
            {
              "videoId": "bWHR0fS9jvQ",
              "title": "MHD - AFRO TRAP Part.7 (La Puissance)",
              "views": 334411839,
              "duration": "2:21",
              "thumbnail": "https://i.ytimg.com/vi/bWHR0fS9jvQ/hq720.jpg"
            },
            {
              "videoId": "EFpGndwMiCQ",
              "title": "MHD - A KELE NTA",
              "views": 164383315,
              "duration": "3:33",
              "thumbnail": "https://i.ytimg.com/vi/EFpGndwMiCQ/hq720.jpg"
            },
            {
              "videoId": "xO2y82caN4U",
              "title": "MHD - Bébé (feat. Dadju)",
              "views": 213730483,
              "duration": "4:21",
              "thumbnail": "https://i.ytimg.com/vi/xO2y82caN4U/hq720.jpg"
            },
            {
              "videoId": "DIfWpLecOOE",
              "title": "MHD - Maman j'ai mal",
              "views": 72755976,
              "duration": "3:23",
              "thumbnail": "https://i.ytimg.com/vi/DIfWpLecOOE/hq720.jpg"
            },
            {
              "videoId": "BnRb5Mf6ayE",
              "title": "MHD - Live Session \"Mansa\"",
              "views": 3418076,
              "duration": "24:31",
              "thumbnail": "https://i.ytimg.com/vi/BnRb5Mf6ayE/hq720.jpg"
            }
          ],
          "songCount": 5
        },
        {
          "name": "Maitre Gims",
          "channel": {
            "id": "UCCB1Byx5yTbLpQaV-rlfmtA",
            "name": "GIMS",
            "image": "https://yt3.googleusercontent.com/MH9TWKPxjVZNjfGbZGLa9D71D-LVpTOPJbkh_abunMIfS6Mzqeh7M4c19eQdcp5i9dTQvIodUA=s88-c-k-c0x00ffffff-no-rj-mo",
            "subscribers": 14800000,
            "verified": true
          },
          "topSongs": [
            {
              "videoId": "6TpyRE_juyA",
              "title": "GIMS - Est-ce que tu m'aimes ? (Clip officiel)",
              "views": 589177898,
              "duration": "4:02",
              "thumbnail": "https://i.ytimg.com/vi/6TpyRE_juyA/hq720.jpg"
            },
            {
              "videoId": "hsfDq30EZGQ",
              "title": "Maître Gims - Est-ce Que Tu M'aimes ? (Lyrics)",
              "views": 39140019,
              "duration": "3:56",
              "thumbnail": "https://i.ytimg.com/vi/hsfDq30EZGQ/hq720.jpg"
            },
            {
              "videoId": "4bPGxLxogvw",
              "title": "GIMS - Sapés comme jamais (Clip officiel) ft. Niska",
              "views": 667443279,
              "duration": "3:26",
              "thumbnail": "https://i.ytimg.com/vi/4bPGxLxogvw/hq720.jpg"
            },
            {
              "videoId": "F_rEHfLgdcY",
              "title": "GIMS - J'me tire (Clip officiel)",
              "views": 354754124,
              "duration": "4:22",
              "thumbnail": "https://i.ytimg.com/vi/F_rEHfLgdcY/hq720.jpg"
            },
            {
              "videoId": "rMltoD1jCGI",
              "title": "GIMS - Bella (Clip officiel)",
              "views": 658221099,
              "duration": "4:43",
              "thumbnail": "https://i.ytimg.com/vi/rMltoD1jCGI/hq720.jpg"
            }
          ],
          "songCount": 5
        },
        {
          "name": "Martin Solveig",
          "channel": {
            "id": "UCL_XuR9jOkgivUmZGaXPEeA",
            "name": "Martin Solveig",
            "image": "https://yt3.ggpht.com/ytc/AIdro_nr2qRuQOWWSIZTtRDsRZiK3SaqEN6QHIw8HDHo7wXk-ms=s88-c-k-c0x00ffffff-no-rj-mo",
            "subscribers": 342000,
            "verified": true
          },
          "topSongs": [
            {
              "videoId": "94Rq2TX0wj4",
              "title": "Martin Solveig & GTA - Intoxicated (Official Music Video)",
              "views": 199458441,
              "duration": "3:15",
              "thumbnail": "https://i.ytimg.com/vi/94Rq2TX0wj4/hqdefault.jpg"
            },
            {
              "videoId": "kK42LZqO0wA",
              "title": "Martin Solveig & Dragonette - Hello (Official Short Video Version HD)",
              "views": 134432221,
              "duration": "4:13",
              "thumbnail": "https://i.ytimg.com/vi/kK42LZqO0wA/hqdefault.jpg"
            },
            {
              "videoId": "LnET4RKXx5k",
              "title": "Martin Solveig & Dragonette - Hello (Official Music Video) [HD]",
              "views": 26505489,
              "duration": "4:03",
              "thumbnail": "https://i.ytimg.com/vi/LnET4RKXx5k/hqdefault.jpg"
            },
            {
              "videoId": "STmLv9pLuX0",
              "title": "Martin Solveig - All Stars (Official Video) ft. ALMA",
              "views": 53053862,
              "duration": "2:57",
              "thumbnail": "https://i.ytimg.com/vi/STmLv9pLuX0/hq720.jpg"
            },
            {
              "videoId": "KUlv7qraZaM",
              "title": "Martin Solveig - The Night Out (Official Music Video)",
              "views": 13731871,
              "duration": "3:42",
              "thumbnail": "https://i.ytimg.com/vi/KUlv7qraZaM/hqdefault.jpg"
            }
          ],
          "songCount": 5
        },
        {
          "name": "Mylene Farmer",
          "channel": {
            "id": "UC8bXAHcitOUnxe7cFg6Curg",
            "name": "Mylène Farmer",
            "image": "https://yt3.googleusercontent.com/gz2It_2H49vWRqfXVBc69528H8t5JiCtx8KS-Yt-t_Y9S3fl6jJ8Rr6dHDxzrheDsagl-29CRdc=s88-c-k-c0x00ffffff-no-rj-mo",
            "subscribers": 834000,
            "verified": true
          },
          "topSongs": [
            {
              "videoId": "w2wrHUQhdfI",
              "title": "Mylène Farmer - L'Amour n'est rien... (Clip Officiel)",
              "views": 32541188,
              "duration": "3:43",
              "thumbnail": "https://i.ytimg.com/vi/w2wrHUQhdfI/hq720.jpg"
            },
            {
              "videoId": "fdqn6JekZwc",
              "title": "Mylène Farmer - Appelle mon numéro  (Clip Officiel)",
              "views": 33321147,
              "duration": "4:35",
              "thumbnail": "https://i.ytimg.com/vi/fdqn6JekZwc/hq720.jpg"
            },
            {
              "videoId": "kD4TmRbk6K0",
              "title": "Mylène Farmer - Timeless 2013 (Tradução) (Live Legendado)",
              "views": 11788,
              "duration": "2:06:44",
              "thumbnail": "https://i.ytimg.com/vi/kD4TmRbk6K0/hq720.jpg"
            },
            {
              "videoId": "r1Le-dAocI8",
              "title": "Mylène Farmer - Désenchantée (Stade de France Live)",
              "views": 9390408,
              "duration": "11:05",
              "thumbnail": "https://i.ytimg.com/vi/r1Le-dAocI8/hq720.jpg"
            },
            {
              "videoId": "dnPLBWXzaw8",
              "title": "Mylène Farmer live Nevermore 2023 with English Subtitles",
              "views": 181823,
              "duration": "2:04:28",
              "thumbnail": "https://i.ytimg.com/vi/dnPLBWXzaw8/hq720.jpg"
            }
          ],
          "songCount": 5
        },
        {
          "name": "NTM",
          "channel": {
            "id": "UCP7XUfKvqruYCYYBtRH8LRg",
            "name": "NTM Gaming TV",
            "image": "https://yt3.googleusercontent.com/ytc/AIdro_mm104ooaAj8HnT-CLL63vnxJAMfRULlHtt_oyvqLYbdrg=s88-c-k-c0x00ffffff-no-rj-mo",
            "subscribers": 17500,
            "verified": false
          },
          "topSongs": [
            {
              "videoId": "x7trJTujKv8",
              "title": "Suprême NTM - Pose ton Gun (Clip officiel)",
              "views": 32595021,
              "duration": "3:39",
              "thumbnail": "https://i.ytimg.com/vi/x7trJTujKv8/hq720.jpg"
            },
            {
              "videoId": "biYdUZXfz9I",
              "title": "Suprême NTM - Laisse pas traîner ton fils (Clip officiel)",
              "views": 87631634,
              "duration": "3:57",
              "thumbnail": "https://i.ytimg.com/vi/biYdUZXfz9I/hq720.jpg"
            },
            {
              "videoId": "Wn1Ny-RNAG8",
              "title": "Suprême NTM - Seine Saint-Denis Style (Clip officiel)",
              "views": 7427728,
              "duration": "2:06",
              "thumbnail": "https://i.ytimg.com/vi/Wn1Ny-RNAG8/hq720.jpg"
            },
            {
              "videoId": "zKFqbyDR6M4",
              "title": "Suprême NTM - That's My People (Clip officiel)",
              "views": 38781407,
              "duration": "4:12",
              "thumbnail": "https://i.ytimg.com/vi/zKFqbyDR6M4/hq720.jpg"
            },
            {
              "videoId": "P7dtLmwt6PY",
              "title": "LX - N.T.M (Jambeatz)",
              "views": 18574626,
              "duration": "2:40",
              "thumbnail": "https://i.ytimg.com/vi/P7dtLmwt6PY/hq720.jpg"
            }
          ],
          "songCount": 5
        },
        {
          "name": "Nekfeu",
          "channel": {
            "id": "UCvuoyvO5ae3EpxQoLErgR2Q",
            "name": "Nekfeu",
            "image": "https://yt3.ggpht.com/ytc/AIdro_mBDsJATzIw1gBQSQ3VXrTS2KTMp1Dx0tLHleY-H6U=s88-c-k-c0x00ffffff-no-rj-mo",
            "subscribers": 1650000,
            "verified": true
          },
          "topSongs": [
            {
              "videoId": "YltjliK0ZeA",
              "title": "Nekfeu - On Verra",
              "views": 166328608,
              "duration": "3:26",
              "thumbnail": "https://i.ytimg.com/vi/YltjliK0ZeA/hq720.jpg"
            },
            {
              "videoId": "MiyIg__WNOw",
              "title": "Humanoïde",
              "views": 20518131,
              "duration": "6:27",
              "thumbnail": "https://i.ytimg.com/vi/MiyIg__WNOw/hq720.jpg"
            },
            {
              "videoId": "ViCL1jMZNHc",
              "title": "Galatée",
              "views": 25945801,
              "duration": "3:55",
              "thumbnail": "https://i.ytimg.com/vi/ViCL1jMZNHc/hq720.jpg"
            },
            {
              "videoId": "yEyTe-QzyfQ",
              "title": "Nekfeu - Egérie",
              "views": 41757805,
              "duration": "4:04",
              "thumbnail": "https://i.ytimg.com/vi/yEyTe-QzyfQ/hq720.jpg"
            },
            {
              "videoId": "RmS3oyRVG8k",
              "title": "Risibles amours",
              "views": 14392971,
              "duration": "8:46",
              "thumbnail": "https://i.ytimg.com/vi/RmS3oyRVG8k/hq720.jpg"
            }
          ],
          "songCount": 5
        },
        {
          "name": "Ninho",
          "channel": {
            "id": "UCXdHJabqwLJ3NvPfx6XmS5Q",
            "name": "Ninho",
            "image": "https://yt3.googleusercontent.com/wnH-FYay_UqOuiUWcqCsQG8i-DZlKxlAWJuiJOEdKxQJ_YmN1-fy0Jih553EZpw8BPuk3QcyWdQ=s88-c-k-c0x00ffffff-no-rj-mo",
            "subscribers": 6340000,
            "verified": true
          },
          "topSongs": [
            {
              "videoId": "BJwovrr6XzI",
              "title": "La vie qu'on mène",
              "views": 214504405,
              "duration": "3:14",
              "thumbnail": "https://i.ytimg.com/vi/BJwovrr6XzI/hq720.jpg"
            },
            {
              "videoId": "dIJuNqS9c3w",
              "title": "Ninho - PILIER (Clip officiel)",
              "views": 11915403,
              "duration": "3:14",
              "thumbnail": "https://i.ytimg.com/vi/dIJuNqS9c3w/hqdefault.jpg"
            },
            {
              "videoId": "kh6Uw9XNI_M",
              "title": "So La Lune (feat. Ninho) - A Little A Lot (Visualizer)",
              "views": 158782,
              "duration": "3:00",
              "thumbnail": "https://i.ytimg.com/vi/kh6Uw9XNI_M/hq720.jpg"
            },
            {
              "videoId": "HqJ1qP05Si0",
              "title": "Ninho - Tout en Gucci (Clip officiel)",
              "views": 165297430,
              "duration": "4:13",
              "thumbnail": "https://i.ytimg.com/vi/HqJ1qP05Si0/hq720.jpg"
            },
            {
              "videoId": "ifNfpzkoY9s",
              "title": "Ninho - Lettre à une femme (Clip officiel)",
              "views": 168896704,
              "duration": "2:39",
              "thumbnail": "https://i.ytimg.com/vi/ifNfpzkoY9s/hq720.jpg"
            }
          ],
          "songCount": 5
        },
        {
          "name": "Orelsan",
          "channel": {
            "id": "UCEnFzIYw3BrndPCddyQ6c5A",
            "name": "orelsan",
            "image": "https://yt3.googleusercontent.com/Gvudix3mR0S6xXypsuORhQTTpiJyTQURNmScHo9aYiCooOz3aVJpYjR58STAOc6YdqxP_u07T-Q=s88-c-k-c0x00ffffff-no-rj-mo",
            "subscribers": 2140000,
            "verified": true
          },
          "topSongs": [
            {
              "videoId": "2bjk26RwjyU",
              "title": "OrelSan - Basique [CLIP OFFICIEL]",
              "views": 117674761,
              "duration": "2:43",
              "thumbnail": "https://i.ytimg.com/vi/2bjk26RwjyU/hq720.jpg"
            },
            {
              "videoId": "dq6G2YWoRqA",
              "title": "OrelSan - Tout va bien [CLIP OFFICIEL]",
              "views": 53399611,
              "duration": "2:38",
              "thumbnail": "https://i.ytimg.com/vi/dq6G2YWoRqA/hq720.jpg"
            },
            {
              "videoId": "tkrdvrf0W-k",
              "title": "OrelSan - Encore une fois (feat. Yamê) [CLIP OFFICIEL]",
              "views": 2283411,
              "duration": "2:54",
              "thumbnail": "https://i.ytimg.com/vi/tkrdvrf0W-k/hq720.jpg"
            },
            {
              "videoId": "zFknl7OAV0c",
              "title": "OrelSan - L'odeur de l'essence [CLIP OFFICIEL]",
              "views": 33005481,
              "duration": "4:45",
              "thumbnail": "https://i.ytimg.com/vi/zFknl7OAV0c/hq720.jpg"
            },
            {
              "videoId": "ZT6IYZor9e8",
              "title": "OrelSan - Jour meilleur [CLIP OFFICIEL]",
              "views": 34769198,
              "duration": "5:05",
              "thumbnail": "https://i.ytimg.com/vi/ZT6IYZor9e8/hq720.jpg"
            }
          ],
          "songCount": 5
        },
        {
          "name": "PNL",
          "channel": {
            "id": "UCtBjt766LG9EDVKZx4Q4IHw",
            "name": "PNL",
            "image": "https://yt3.ggpht.com/ytc/AIdro_mUZ0Kd0roL7s4tNtd2zdrP7gOyhBvt5Gxw8zg89XD_rQA=s88-c-k-c0x00ffffff-no-rj-mo",
            "subscribers": 6520000,
            "verified": true
          },
          "topSongs": [
            {
              "videoId": "u8bHjdljyLw",
              "title": "PNL - Blanka [Clip Officiel]",
              "views": 142086147,
              "duration": "5:05",
              "thumbnail": "https://i.ytimg.com/vi/u8bHjdljyLw/hq720.jpg"
            },
            {
              "videoId": "umF1kfVujhM",
              "title": "PNL - Le monde ou rien [Official Video]",
              "views": 155598251,
              "duration": "4:36",
              "thumbnail": "https://i.ytimg.com/vi/umF1kfVujhM/hqdefault.jpg"
            },
            {
              "videoId": "Vl-GJaitlNs",
              "title": "PNL - A l'Ammoniaque [Official Video]",
              "views": 195378302,
              "duration": "5:47",
              "thumbnail": "https://i.ytimg.com/vi/Vl-GJaitlNs/hq720.jpg"
            },
            {
              "videoId": "BtyHYIpykN0",
              "title": "PNL - Au DD [Official Video]",
              "views": 236353829,
              "duration": "4:51",
              "thumbnail": "https://i.ytimg.com/vi/BtyHYIpykN0/hq720.jpg"
            },
            {
              "videoId": "vNpl-M3_9_o",
              "title": "PNL - Deux Frères [Clip Officiel]",
              "views": 114905384,
              "duration": "7:39",
              "thumbnail": "https://i.ytimg.com/vi/vNpl-M3_9_o/hq720.jpg"
            }
          ],
          "songCount": 5
        },
        {
          "name": "Passi",
          "channel": {
            "id": "UCl8Mu-TirNwBzWW1nEIRQrg",
            "name": "Passi Officiel",
            "image": "https://yt3.ggpht.com/ytc/AIdro_lW7MgUdwZqlWOQlEwPk-A0S2c0rG2q7kXtowGwWQYty2M=s88-c-k-c0x00ffffff-no-rj-mo",
            "subscribers": 154000,
            "verified": true
          },
          "topSongs": [
            {
              "videoId": "Vek3FUkdaxM",
              "title": "PASSI - Io e Palmieri (Deborah De Luca Remix)",
              "views": 1738481,
              "duration": "4:44",
              "thumbnail": "https://i.ytimg.com/vi/Vek3FUkdaxM/hq720.jpg"
            },
            {
              "videoId": "o6-_zKSf0-E",
              "title": "PASSI",
              "views": 113413,
              "duration": "4:25",
              "thumbnail": "https://i.ytimg.com/vi/o6-_zKSf0-E/hq720.jpg"
            },
            {
              "videoId": "-ejpeAxTDJI",
              "title": "Passi - Reviens Dans Ma Vie (Feat. Jacob Desvarieux et Lorenzo Raphael)[Clip Officiel - HD]",
              "views": 2422387,
              "duration": "3:12",
              "thumbnail": "https://i.ytimg.com/vi/-ejpeAxTDJI/hq720.jpg"
            },
            {
              "videoId": "dvwSVCnLF1Q",
              "title": "Passi - Le Monde est à Moi (Feat. Akhenaton) [Clip Officiel - HD]",
              "views": 14097528,
              "duration": "4:10",
              "thumbnail": "https://i.ytimg.com/vi/dvwSVCnLF1Q/hq720.jpg"
            },
            {
              "videoId": "h--37amvez4",
              "title": "Passi - 79 à 99 (Clip Officiel - HD)",
              "views": 7828734,
              "duration": "3:35",
              "thumbnail": "https://i.ytimg.com/vi/h--37amvez4/hq720.jpg"
            }
          ],
          "songCount": 5
        },
        {
          "name": "Phoenix",
          "channel": {
            "id": "UCNDAbwbXmmgosddFdUyRWwg",
            "name": "welovephoenix",
            "image": "https://yt3.googleusercontent.com/CaT3TsvKuJ9mLrR7_l_DlNo-iOY0agm5txjtUnePfW0nUWmngnmgbIaY0VS6iUR577UZ-jWHsg=s88-c-k-c0x00ffffff-no-rj-mo",
            "subscribers": 235000,
            "verified": true
          },
          "topSongs": [
            {
              "videoId": "i1IKnWDecwA",
              "title": "Phoenix (ft. Cailin Russo and Chrissy Costanza) | Worlds 2019 - League of Legends",
              "views": 179736757,
              "duration": "3:28",
              "thumbnail": "https://i.ytimg.com/vi/i1IKnWDecwA/hq720.jpg"
            },
            {
              "videoId": "4BJDNw7o6so",
              "title": "Phoenix - Lisztomania (Official Video)",
              "views": 23902557,
              "duration": "3:27",
              "thumbnail": "https://i.ytimg.com/vi/4BJDNw7o6so/hqdefault.jpg"
            },
            {
              "videoId": "5JqY-6q-RNA",
              "title": "Fall Out Boy - THE PHOENIX (Animated Lyric Video)",
              "views": 136745727,
              "duration": "4:09",
              "thumbnail": "https://i.ytimg.com/vi/5JqY-6q-RNA/hq720.jpg"
            },
            {
              "videoId": "5hDZbroaQDc",
              "title": "Fall Out Boy - The Phoenix (Official Video) - Part 2 of 11",
              "views": 112987516,
              "duration": "4:23",
              "thumbnail": "https://i.ytimg.com/vi/5hDZbroaQDc/hq720.jpg"
            },
            {
              "videoId": "yH88qRmgkGI",
              "title": "Netrum & Halvorsen - Phoenix | Synthwave | NCS - Copyright Free Music",
              "views": 14739977,
              "duration": "3:58",
              "thumbnail": "https://i.ytimg.com/vi/yH88qRmgkGI/hq720.jpg"
            }
          ],
          "songCount": 5
        },
        {
          "name": "Serge Gainsbourg",
          "channel": {
            "id": "UCMqAEhVGBz5WrBH-Ph3u0vg",
            "name": "Serge Gainsbourg",
            "image": "https://yt3.ggpht.com/ytc/AIdro_lCRCaVFcOvjHxKoAr2g-0olHqd0IB0vNIAQHA_E2d4BQ=s88-c-k-c0x00ffffff-no-rj-mo",
            "subscribers": 127000,
            "verified": true
          },
          "topSongs": [
            {
              "videoId": "unYu22Ign1E",
              "title": "French Kids Paying Tribute to Serge Gainsbourg (1988)",
              "views": 676544,
              "duration": "2:44",
              "thumbnail": "https://i.ytimg.com/vi/unYu22Ign1E/hqdefault.jpg"
            },
            {
              "videoId": "GlpDf6XX_j0",
              "title": "Serge Gainsbourg & Jane Birkin - Je t'aime... moi non plus/Original videoclip (Fontana 1969)",
              "views": 20292289,
              "duration": "4:21",
              "thumbnail": "https://i.ytimg.com/vi/GlpDf6XX_j0/hqdefault.jpg"
            },
            {
              "videoId": "Stz8SQ_xeNk",
              "title": "Serge Gainsbourg - L'eau à la bouche (1960)",
              "views": 5934152,
              "duration": "2:24",
              "thumbnail": "https://i.ytimg.com/vi/Stz8SQ_xeNk/hq720.jpg"
            },
            {
              "videoId": "V6gjzNm6dA0",
              "title": "Serge Gainsbourg - La Javanaise (1968)",
              "views": 8854106,
              "duration": "2:27",
              "thumbnail": "https://i.ytimg.com/vi/V6gjzNm6dA0/hq720.jpg"
            },
            {
              "videoId": "6RAJdafk1Y8",
              "title": "Serge Gainsbourg - Je suis venu te dire que je m'en vais",
              "views": 4168863,
              "duration": "3:25",
              "thumbnail": "https://i.ytimg.com/vi/6RAJdafk1Y8/hqdefault.jpg"
            }
          ],
          "songCount": 5
        },
        {
          "name": "Sexion d'Assaut",
          "channel": {},
          "topSongs": [],
          "songCount": 0
        },
        {
          "name": "Slimane",
          "channel": {
            "id": "UChvOLOXJLQrUW_g9wvYAVLw",
            "name": "Slimane",
            "image": "https://yt3.googleusercontent.com/wBLjC-LJiGxq5uswLKjfb_VZICWT8kkd3Kdogs2Wqmn7IGVx-a1SvjEtJIAqQtUiwaP70_mHRA=s88-c-k-c0x00ffffff-no-rj-mo",
            "subscribers": 1430000,
            "verified": true
          },
          "topSongs": [
            {
              "videoId": "-XyLecY2JyE",
              "title": "Slimane - Mon Amour (LIVE) | France 🇫🇷 | Grand Final | Eurovision 2024",
              "views": 32457609,
              "duration": "3:18",
              "thumbnail": "https://i.ytimg.com/vi/-XyLecY2JyE/hq720.jpg"
            },
            {
              "videoId": "bal8oESDH7s",
              "title": "Slimane - Mon Amour (Live Performance)",
              "views": 59735656,
              "duration": "3:00",
              "thumbnail": "https://i.ytimg.com/vi/bal8oESDH7s/hq720.jpg"
            },
            {
              "videoId": "d6BzCEkGd3I",
              "title": "VITAA & SLIMANE - Avant toi (Clip Officiel)",
              "views": 235221878,
              "duration": "3:44",
              "thumbnail": "https://i.ytimg.com/vi/d6BzCEkGd3I/hq720.jpg"
            },
            {
              "videoId": "TtW_QqXN0Hc",
              "title": "Slimane - A fleur de toi ( Cover )",
              "views": 80933021,
              "duration": "4:14",
              "thumbnail": "https://i.ytimg.com/vi/TtW_QqXN0Hc/hq720.jpg"
            },
            {
              "videoId": "C00iuatMQ-g",
              "title": "Vitaa – A Fleur de Toi | Slimane Nebchi | The Voice France 2016 | Blind Audition",
              "views": 34663425,
              "duration": "2:31",
              "thumbnail": "https://i.ytimg.com/vi/C00iuatMQ-g/hq720.jpg"
            }
          ],
          "songCount": 5
        },
        {
          "name": "Soprano",
          "channel": {
            "id": "UCYne4N06sHVhRBXS0Lq5D8g",
            "name": "Soprano Officiel",
            "image": "https://yt3.googleusercontent.com/ZPDYKEI_nkIPgiOltY6VoDx6LPv9wokbBy2WeeMe1Y0rsDl9G5lFpvFuhFgAVLE8zc1jaaVK5w=s88-c-k-c0x00ffffff-no-rj-mo",
            "subscribers": 4890000,
            "verified": true
          },
          "topSongs": [
            {
              "videoId": "YHD2xZcsHZY",
              "title": "Soprano",
              "views": 280263,
              "duration": "2:00",
              "thumbnail": "https://i.ytimg.com/vi/YHD2xZcsHZY/hq720.jpg"
            },
            {
              "videoId": "jXCxdLvdscU",
              "title": "Мот feat. Ани Лорак - Сопрано (премьера клипа, 2017)",
              "views": 220529304,
              "duration": "3:40",
              "thumbnail": "https://i.ytimg.com/vi/jXCxdLvdscU/hq720.jpg"
            },
            {
              "videoId": "YuBeBjqKSGQ",
              "title": "The Magic Flute – Queen of the Night aria (Mozart; Diana Damrau, The Royal Opera)",
              "views": 78100569,
              "duration": "3:01",
              "thumbnail": "https://i.ytimg.com/vi/YuBeBjqKSGQ/hq720.jpg"
            },
            {
              "videoId": "ErN8JDGjrHQ",
              "title": "Patricia JANEČKOVÁ: \"Frühlingsstimmen\" (Johann Strauss II)",
              "views": 8833224,
              "duration": "7:39",
              "thumbnail": "https://i.ytimg.com/vi/ErN8JDGjrHQ/hq720.jpg"
            },
            {
              "videoId": "0JZxZj6bFzQ",
              "title": "The Divas - Most Beautiful Soprano Arias",
              "views": 415057,
              "duration": "2:31:11",
              "thumbnail": "https://i.ytimg.com/vi/0JZxZj6bFzQ/hq720.jpg"
            }
          ],
          "songCount": 5
        },
        {
          "name": "Stromae",
          "channel": {
            "id": "UCXF0YCBWewAj3RytJUAivGA",
            "name": "Stromae",
            "image": "https://yt3.googleusercontent.com/gpe4ud6Ub2Zsi07HLpH-eYe0LPsJe2gRNo0J1EeKoitnmPf5qsZuOKjOGCkLioIX825t5mPPPFk=s88-c-k-c0x00ffffff-no-rj-mo",
            "subscribers": 8150000,
            "verified": true
          },
          "topSongs": [
            {
              "videoId": "VHoT4N43jK8",
              "title": "Stromae - Alors on danse (Official Video)",
              "views": 538236642,
              "duration": "3:55",
              "thumbnail": "https://i.ytimg.com/vi/VHoT4N43jK8/hq720.jpg"
            },
            {
              "videoId": "CW7gfrTlr0Y",
              "title": "Stromae - Santé | The Tonight Show Starring Jimmy Fallon",
              "views": 61060395,
              "duration": "3:17",
              "thumbnail": "https://i.ytimg.com/vi/CW7gfrTlr0Y/hq720.jpg"
            },
            {
              "videoId": "j-RpvIuazmc",
              "title": "Stromae, Pomme - “Ma Meilleure Ennemie” (dari Arcane Season 2) [Official Music Video]",
              "views": 55571264,
              "duration": "2:49",
              "thumbnail": "https://i.ytimg.com/vi/j-RpvIuazmc/hq720.jpg"
            },
            {
              "videoId": "M7Z2tgJo8Hg",
              "title": "Stromae - Fils de joie (Official Video)",
              "views": 66509397,
              "duration": "3:57",
              "thumbnail": "https://i.ytimg.com/vi/M7Z2tgJo8Hg/hq720.jpg"
            },
            {
              "videoId": "6dkDepLX0rk",
              "title": "Stromae: Tiny Desk Concert",
              "views": 19048988,
              "duration": "16:15",
              "thumbnail": "https://i.ytimg.com/vi/6dkDepLX0rk/hq720.jpg"
            }
          ],
          "songCount": 5
        },
        {
          "name": "Vanessa Paradis",
          "channel": {
            "id": "UCGaRGxzgoNJ9JDJc4tKsBrw",
            "name": "Vanessa Paradis",
            "image": "https://yt3.googleusercontent.com/7QZtD-unPecOG4xWhIz4DTi8hY47IDfC7UnMwFpewNMMG5-O-75bf-PntfMnUDg33f3-8qbF=s88-c-k-c0x00ffffff-no-rj-mo",
            "subscribers": 279000,
            "verified": true
          },
          "topSongs": [
            {
              "videoId": "WXnR7iZy0ZM",
              "title": "Vanessa Paradis - Be My Baby",
              "views": 9531922,
              "duration": "3:41",
              "thumbnail": "https://i.ytimg.com/vi/WXnR7iZy0ZM/hq720.jpg"
            },
            {
              "videoId": "IKxMTFvo_0s",
              "title": "Vanessa Paradis Joe le taxi live.avi",
              "views": 19530255,
              "duration": "3:24",
              "thumbnail": "https://i.ytimg.com/vi/IKxMTFvo_0s/hqdefault.jpg"
            },
            {
              "videoId": "QhYbZkz5EKA",
              "title": "Kehidupan Nyata Vanessa Paradis",
              "views": 1635347,
              "duration": "1:14:08",
              "thumbnail": "https://i.ytimg.com/vi/QhYbZkz5EKA/hqdefault.jpg"
            },
            {
              "videoId": "Ulay2FvUEd8",
              "title": "Vanessa Paradis - Joe Le Taxi (Clip Officiel remasterisé)",
              "views": 84068173,
              "duration": "3:56",
              "thumbnail": "https://i.ytimg.com/vi/Ulay2FvUEd8/hq720.jpg"
            },
            {
              "videoId": "m0OKzp0-T1c",
              "title": "Vanessa Paradis 1992 Be My Baby (Full HD)",
              "views": 26139,
              "duration": "3:32",
              "thumbnail": "https://i.ytimg.com/vi/m0OKzp0-T1c/hq720.jpg"
            }
          ],
          "songCount": 5
        },
        {
          "name": "Vitaa",
          "channel": {
            "id": "UC6atFS0kNdJR-EuSa_I1Kkw",
            "name": "VITAA",
            "image": "https://yt3.googleusercontent.com/vcaOcldPrAD2DmwOMUPrcHVpAnm4JgTtgurtzDwZc79JngZdVgzeQJ3sWI2hKA7cRBq-kEtgzQ=s88-c-k-c0x00ffffff-no-rj-mo",
            "subscribers": 1780000,
            "verified": true
          },
          "topSongs": [
            {
              "videoId": "H-DosCwPCNA",
              "title": "Vitaa - A Fleur de Toi",
              "views": 116927639,
              "duration": "4:27",
              "thumbnail": "https://i.ytimg.com/vi/H-DosCwPCNA/hq720.jpg"
            },
            {
              "videoId": "Y_G9UWfoZns",
              "title": "VITAA - Je n'oublie pas (Clip Officiel)",
              "views": 24912715,
              "duration": "3:48",
              "thumbnail": "https://i.ytimg.com/vi/Y_G9UWfoZns/hq720.jpg"
            },
            {
              "videoId": "d6BzCEkGd3I",
              "title": "VITAA & SLIMANE - Avant toi (Clip Officiel)",
              "views": 235221878,
              "duration": "3:44",
              "thumbnail": "https://i.ytimg.com/vi/d6BzCEkGd3I/hq720.jpg"
            },
            {
              "videoId": "3SoSpZTcxVo",
              "title": "VITAA - IT HURT (Official Music Video)",
              "views": 879742,
              "duration": "3:06",
              "thumbnail": "https://i.ytimg.com/vi/3SoSpZTcxVo/hq720.jpg"
            },
            {
              "videoId": "TwhoaPgBwI8",
              "title": "Diam's - Confessions nocturnes feat. Vitaa (Clip officiel)",
              "views": 175746474,
              "duration": "5:23",
              "thumbnail": "https://i.ytimg.com/vi/TwhoaPgBwI8/hq720.jpg"
            }
          ],
          "songCount": 5
        },
        {
          "name": "Zaz",
          "channel": {
            "id": "UCVwvQm_80GlHzPh7krv3KwA",
            "name": "Zaz",
            "image": "https://yt3.googleusercontent.com/SjqhyhrHMMbTyblaqkQOa5QXNh7yfd7aSHW2DxUPKp7OyLh5-bF6MIEniErfl3kA0h7wxUKu=s88-c-k-c0x00ffffff-no-rj-mo",
            "subscribers": 1770000,
            "verified": true
          },
          "topSongs": [
            {
              "videoId": "0TFNGRYMz1U",
              "title": "ZAZ - Je veux (Clip officiel)",
              "views": 124510067,
              "duration": "3:37",
              "thumbnail": "https://i.ytimg.com/vi/0TFNGRYMz1U/hq720.jpg"
            },
            {
              "videoId": "6THHrPyZQuQ",
              "title": "ZAZ – Qué vendrá (Clip officiel)",
              "views": 114478560,
              "duration": "3:02",
              "thumbnail": "https://i.ytimg.com/vi/6THHrPyZQuQ/hq720.jpg"
            },
            {
              "videoId": "lWIhYWJsdB0",
              "title": "Zaz à Montmartre   Les passants",
              "views": 1111383,
              "duration": "4:21",
              "thumbnail": "https://i.ytimg.com/vi/lWIhYWJsdB0/hqdefault.jpg"
            },
            {
              "videoId": "_amuE1tJbXw",
              "title": "Concert complet de ZAZ  @ Francofolies La Rochelle 2014",
              "views": 2175887,
              "duration": "1:20:52",
              "thumbnail": "https://i.ytimg.com/vi/_amuE1tJbXw/hq720.jpg"
            },
            {
              "videoId": "5ZDsCJ4rGD4",
              "title": "ZAZ - Si jamais j'oublie (Clip officiel)",
              "views": 124958307,
              "duration": "3:27",
              "thumbnail": "https://i.ytimg.com/vi/5ZDsCJ4rGD4/hq720.jpg"
            }
          ],
          "songCount": 5
        }
      ]
    },
    "gospel": {
      "count": 15,
      "artists": [
        {
          "name": "Dan Luiten",
          "channel": {
            "id": "UCErG0KOLFjub3_volzSTxYA",
            "name": "Dan Luiten",
            "image": "https://yt3.ggpht.com/ytc/AIdro_ltm9T_2kZCHZ2s4YDgKRLzJFhFgdbD35xZSenNLT3xtQ=s88-c-k-c0x00ffffff-no-rj-mo",
            "subscribers": 124000,
            "verified": true
          },
          "topSongs": [
            {
              "videoId": "pYleLWn5HV8",
              "title": "Dans la tempête, Dieu est mon rocher",
              "views": 4782,
              "duration": "1:36",
              "thumbnail": "https://i.ytimg.com/vi/pYleLWn5HV8/hq720.jpg"
            },
            {
              "videoId": "bGOP2fOq1B4",
              "title": "JE T'AIME À JAMAIS (Clip Officiel LIVE) - Dan Luiten - 2e single de l'album \"Sur la Terre\"",
              "views": 2743486,
              "duration": "5:59",
              "thumbnail": "https://i.ytimg.com/vi/bGOP2fOq1B4/hq720.jpg"
            },
            {
              "videoId": "ohFmz2DAXFQ",
              "title": "Dan Luiten - Ébloui / Gloire à ton nom / Un souffle nouveau / Majestueux",
              "views": 2012495,
              "duration": "29:50",
              "thumbnail": "https://i.ytimg.com/vi/ohFmz2DAXFQ/hq720.jpg"
            },
            {
              "videoId": "1Jm7BbIfP8Y",
              "title": "Session d'adoration acoustique - Dan Luiten et Marie Zamor - EMCI Musique",
              "views": 84171,
              "duration": "37:27",
              "thumbnail": "https://i.ytimg.com/vi/1Jm7BbIfP8Y/hq720.jpg"
            },
            {
              "videoId": "LOZG3u-PqAo",
              "title": "Emmanuel - Dan Luiten & Chris et Laura Christensen (EXO) (Live)",
              "views": 78356,
              "duration": "5:21",
              "thumbnail": "https://i.ytimg.com/vi/LOZG3u-PqAo/hq720.jpg"
            }
          ],
          "songCount": 5
        },
        {
          "name": "Glorious",
          "channel": {},
          "topSongs": [
            {
              "videoId": "nomxXk6Q1rk",
              "title": "Glorious - David Archuleta | One Voice Children's Choir | Kids Cover (Official Music Video)",
              "views": 35498696,
              "duration": "3:13",
              "thumbnail": "https://i.ytimg.com/vi/nomxXk6Q1rk/hq720.jpg"
            },
            {
              "videoId": "lTDOhoPi7m8",
              "title": "Glorious",
              "views": 2556113,
              "duration": "4:42",
              "thumbnail": "https://i.ytimg.com/vi/lTDOhoPi7m8/hq720.jpg"
            },
            {
              "videoId": "7OrLroFa0AI",
              "title": "MACKLEMORE FEAT SKYLAR GREY - GLORIOUS (OFFICIAL MUSIC VIDEO)",
              "views": 294284249,
              "duration": "4:15",
              "thumbnail": "https://i.ytimg.com/vi/7OrLroFa0AI/hqdefault.jpg"
            },
            {
              "videoId": "XTZlCcoG8GM",
              "title": "Weird Genius 'Glorious' - Official Song of the FIFA U-20 World Cup Argentina 2023™ [Lyric Video]",
              "views": 398010,
              "duration": "3:30",
              "thumbnail": "https://i.ytimg.com/vi/XTZlCcoG8GM/hq720.jpg"
            },
            {
              "videoId": "kjbbvtplYSk",
              "title": "Glorious - Official Song of the FIFA U-20 World Cup Argentina 2023™",
              "views": 3193087,
              "duration": "3:30",
              "thumbnail": "https://i.ytimg.com/vi/kjbbvtplYSk/hq720.jpg"
            }
          ],
          "songCount": 5
        },
        {
          "name": "Gospel Pour 100 Voix",
          "channel": {
            "id": "UCVvKYRKVpPnu6ZV9WNXFodA",
            "name": "The 100 Voices Of Gospel (Gospel Pour 100 Voix)",
            "image": "https://yt3.googleusercontent.com/ytc/AIdro_lv_fn6IRKEUefeUvxZolhwRi3D528jJsv-TwgRDQogMQ=s88-c-k-c0x00ffffff-no-rj-mo",
            "subscribers": 13100,
            "verified": false
          },
          "topSongs": [
            {
              "videoId": "dK_FiuyVU2Y",
              "title": "The 100 Voices Of Gospel go for gold! | Week 2 Auditions | Britain’s Got Talent 2016",
              "views": 28095241,
              "duration": "7:13",
              "thumbnail": "https://i.ytimg.com/vi/dK_FiuyVU2Y/hqdefault.jpg"
            },
            {
              "videoId": "2lZwXewd_eU",
              "title": "THE DELIVERANCE TOUR 2025/2026 - The 100 Voices of Gospel (Official Teaser)",
              "views": 24892,
              "duration": "1:22",
              "thumbnail": "https://i.ytimg.com/vi/2lZwXewd_eU/hqdefault.jpg"
            },
            {
              "videoId": "5oMVi9oMms8",
              "title": "I m Going Up Yonder interprété par Gospel Pour 100 Voix \"The 100 Voices Of Gospel\"",
              "views": 88895,
              "duration": "6:50",
              "thumbnail": "https://i.ytimg.com/vi/5oMVi9oMms8/hq720.jpg"
            },
            {
              "videoId": "y1SJDjerSKQ",
              "title": "Hallelujah | 100 Voices Of Gospel (Gospel Pour 100 Voix)",
              "views": 147778,
              "duration": "3:27",
              "thumbnail": "https://i.ytimg.com/vi/y1SJDjerSKQ/hq720.jpg"
            },
            {
              "videoId": "Q4P_OVKHNaE",
              "title": "Amazing Grace : Nana Mouskouri & Gospel for 100 Voices. \"Gospel Pour 100 Voix\"",
              "views": 2280267,
              "duration": "4:31",
              "thumbnail": "https://i.ytimg.com/vi/Q4P_OVKHNaE/hq720.jpg"
            }
          ],
          "songCount": 5
        },
        {
          "name": "Helene Segara",
          "channel": {
            "id": "UCr-NOOFtG2F7g7l5GoVHr7w",
            "name": "Hélène Ségara",
            "image": "https://yt3.googleusercontent.com/Tqp_j6Av5LiVHJYJENyqjrU4QJWo1IJaf30HphVdDyYDnwXXPhxN-i-kJGlgWT6EQlo4lUErhA=s88-c-k-c0x00ffffff-no-rj-mo",
            "subscribers": 209000,
            "verified": true
          },
          "topSongs": [
            {
              "videoId": "C7asfuBtADo",
              "title": "Helene Segara - elle tu l`aimes",
              "views": 22948352,
              "duration": "4:16",
              "thumbnail": "https://i.ytimg.com/vi/C7asfuBtADo/hqdefault.jpg"
            },
            {
              "videoId": "PhwVo33uq4o",
              "title": "Hélène Segara - L'amour est un soleil (Clip Officiel)",
              "views": 6763506,
              "duration": "3:55",
              "thumbnail": "https://i.ytimg.com/vi/PhwVo33uq4o/hq720.jpg"
            },
            {
              "videoId": "eMwGN7yqBgg",
              "title": "Hélène Segara - Encore une fois (Clip Officiel)",
              "views": 1352234,
              "duration": "3:54",
              "thumbnail": "https://i.ytimg.com/vi/eMwGN7yqBgg/hq720.jpg"
            },
            {
              "videoId": "qmqruqnj99M",
              "title": "Hélène Ségara, Joe Dassin - Et si tu n'existais pas (Clip officiel)",
              "views": 36711936,
              "duration": "3:34",
              "thumbnail": "https://i.ytimg.com/vi/qmqruqnj99M/hq720.jpg"
            },
            {
              "videoId": "otoXMBkkP08",
              "title": "Hélène Segara - Tu vas me quitter (Clip Officiel)",
              "views": 5349019,
              "duration": "3:43",
              "thumbnail": "https://i.ytimg.com/vi/otoXMBkkP08/hq720.jpg"
            }
          ],
          "songCount": 5
        },
        {
          "name": "Hillsong Paris",
          "channel": {
            "id": "UCgeaBz6W__FMB1lekw7N9Wg",
            "name": "Hillsong France",
            "image": "https://yt3.googleusercontent.com/ytc/AIdro_kxmowwofOxW1CIgMMUPxhNu0sgeJdhdisTjGB8Q2ExjQ=s88-c-k-c0x00ffffff-no-rj-mo",
            "subscribers": 15400,
            "verified": false
          },
          "topSongs": [
            {
              "videoId": "Oll45B7cIRY",
              "title": "Dimanche 24 Mai 12h15 | Service de baptêmes et Pentecôte | Église Hillsong",
              "views": 294,
              "duration": "1:45:14",
              "thumbnail": "https://i.ytimg.com/vi/Oll45B7cIRY/hq720.jpg"
            },
            {
              "videoId": "GMDdiLDVPHU",
              "title": "Viens toucher ma vie (L'église en ligne) | Hillsong France",
              "views": 8890241,
              "duration": "6:57",
              "thumbnail": "https://i.ytimg.com/vi/GMDdiLDVPHU/hq720.jpg"
            },
            {
              "videoId": "_1HGZ_9aRhI",
              "title": "Hillsong Worship Best Praise Songs Collection 2023 – Gospel Christian Songs Of Hillsong Worship",
              "views": 8955340,
              "duration": "1:17:50",
              "thumbnail": "https://i.ytimg.com/vi/_1HGZ_9aRhI/hq720.jpg"
            },
            {
              "videoId": "XlgVNdmc6ZI",
              "title": "Compilation Hillsong en français",
              "views": 1624187,
              "duration": "2:01:22",
              "thumbnail": "https://i.ytimg.com/vi/XlgVNdmc6ZI/hq720.jpg"
            },
            {
              "videoId": "DZEl0I5hpgo",
              "title": "Hillsong en français - Best Praise Songs (Chants de louange et adoration) – Collection 2024",
              "views": 13342,
              "duration": "1:51:38",
              "thumbnail": "https://i.ytimg.com/vi/DZEl0I5hpgo/hqdefault.jpg"
            }
          ],
          "songCount": 5
        },
        {
          "name": "Isabelle Voitier",
          "channel": {
            "id": "UCOkKIVpXHnv3ORbYZW15KUQ",
            "name": "isabelle VOITIER",
            "image": "https://yt3.googleusercontent.com/ytc/AIdro_lcNlUxUeMTVV_RE6jcRP4UZmKa-CWwbuutC1ukIghHGA=s88-c-k-c0x00ffffff-no-rj-mo",
            "subscribers": 22,
            "verified": false
          },
          "topSongs": [
            {
              "videoId": "Oq_JE8lEgh0",
              "title": "Teaser ViCoaching",
              "views": 209,
              "duration": "1:20",
              "thumbnail": "https://i.ytimg.com/vi/Oq_JE8lEgh0/hq720.jpg"
            },
            {
              "videoId": "jYYr7jfSlk4",
              "title": "Interview Isabelle Voitier Deitrick Concert",
              "views": 496,
              "duration": "0:34",
              "thumbnail": "https://i.ytimg.com/vi/jYYr7jfSlk4/hq720.jpg"
            },
            {
              "videoId": "xmeXex-yF2o",
              "title": "Ma prière - Marcel Boungou w/ Isabelle Voitier + Paroles",
              "views": 353477,
              "duration": "5:29",
              "thumbnail": "https://i.ytimg.com/vi/xmeXex-yF2o/hqdefault.jpg"
            },
            {
              "videoId": "7GkFS9ByCpM",
              "title": "VIVRE POUR AIMER ONE MORE DAY (Isabelle Voitier) et  You Deserve It avec Heart for humanity",
              "views": 1968,
              "duration": "4:24",
              "thumbnail": "https://i.ytimg.com/vi/7GkFS9ByCpM/hqdefault.jpg"
            },
            {
              "videoId": "E5O_g8rMdmM",
              "title": "Totale Adoration avec Isabelle Voitier & Total Praise / Culte de Gospel de Paris [13 septembre 2020]",
              "views": 4015,
              "duration": "21:46",
              "thumbnail": "https://i.ytimg.com/vi/E5O_g8rMdmM/hq720.jpg"
            }
          ],
          "songCount": 5
        },
        {
          "name": "JEM",
          "channel": {
            "id": "UC1ZIcgIteuBDs56Rh0e_Evg",
            "name": "JEM",
            "image": "https://yt3.googleusercontent.com/UYiZPkxOlc-wCjoupExaLC63T1iOyoM513GLKeFniv23B5xQ1O3gVLcMu7eTRSqk5eAC9Bo1pg=s88-c-k-c0x00ffffff-no-rj-mo",
            "subscribers": 26000,
            "verified": true
          },
          "topSongs": [
            {
              "videoId": "8XDxhDbtDak",
              "title": "Jem - It's Amazing - Official Video",
              "views": 8902017,
              "duration": "4:02",
              "thumbnail": "https://i.ytimg.com/vi/8XDxhDbtDak/hqdefault.jpg"
            },
            {
              "videoId": "QcuF3MTmxH4",
              "title": "DJ JEM JEM BOAT KECELUP SANTEN MENAWI LUPUT NYUWUN NGAPUNTEN MELODY DRACIN VIRAL TIKTOK TERBARU 2026",
              "views": 99401,
              "duration": "5:57",
              "thumbnail": "https://i.ytimg.com/vi/QcuF3MTmxH4/hq720.jpg"
            },
            {
              "videoId": "Dx85I---Dt8",
              "title": "Wish I",
              "views": 154587,
              "duration": "3:56",
              "thumbnail": "https://i.ytimg.com/vi/Dx85I---Dt8/hqdefault.jpg"
            },
            {
              "videoId": "k53NGe64RBU",
              "title": "Jem - They - Official Video",
              "views": 2659655,
              "duration": "3:21",
              "thumbnail": "https://i.ytimg.com/vi/k53NGe64RBU/hqdefault.jpg"
            },
            {
              "videoId": "oaZ9RHZhkuM",
              "title": "Save Me",
              "views": 338015,
              "duration": "3:34",
              "thumbnail": "https://i.ytimg.com/vi/oaZ9RHZhkuM/hq720.jpg"
            }
          ],
          "songCount": 5
        },
        {
          "name": "Joyce Jonathan",
          "channel": {
            "id": "UCWWuX7gqre-Sa8GjpVY-8QA",
            "name": "Joyce Jonathan",
            "image": "https://yt3.googleusercontent.com/zDJ6aEOEDOspSFPquZbF0HFoA_f5rP6Gw0vfOdKVevMFTkX2Yk57pv6n_IheiBc1FUchWKbRtw=s88-c-k-c0x00ffffff-no-rj-mo",
            "subscribers": 324000,
            "verified": true
          },
          "topSongs": [
            {
              "videoId": "LJln2ghLxEo",
              "title": "Joyce Jonathan feat. Jason Mraz - À la vie comme à la mort [Official Video]",
              "views": 1472556,
              "duration": "3:42",
              "thumbnail": "https://i.ytimg.com/vi/LJln2ghLxEo/hq720.jpg"
            },
            {
              "videoId": "xLDrMhF4a-w",
              "title": "Joyce Jonathan - Caractère",
              "views": 9847371,
              "duration": "4:09",
              "thumbnail": "https://i.ytimg.com/vi/xLDrMhF4a-w/hq720.jpg"
            },
            {
              "videoId": "FsJWSDe44Uk",
              "title": "Joyce Jonathan - Je ne sais pas (Clip officiel)",
              "views": 37343220,
              "duration": "3:42",
              "thumbnail": "https://i.ytimg.com/vi/FsJWSDe44Uk/hqdefault.jpg"
            },
            {
              "videoId": "TxWLybPwBzs",
              "title": "Joyce Jonathan - Ça Ira",
              "views": 60468495,
              "duration": "4:00",
              "thumbnail": "https://i.ytimg.com/vi/TxWLybPwBzs/hq720.jpg"
            },
            {
              "videoId": "vEownqYD9Mk",
              "title": "Joyce Jonathan - Les p'tites jolies choses  [Clip officiel]",
              "views": 2155875,
              "duration": "3:27",
              "thumbnail": "https://i.ytimg.com/vi/vEownqYD9Mk/hq720.jpg"
            }
          ],
          "songCount": 5
        },
        {
          "name": "LTC",
          "channel": {
            "id": "UC_SXaYKRSQ3BTvPJJhXCmeA",
            "name": "LTC OFFICIAL ",
            "image": "https://yt3.ggpht.com/Jai1YbdfOZm-yspQcJDgkM45q5aZx3nzHDDaGKIGVr8bAxD0gJVS4xPKCSf-qY_W3ZJXaf6C=s88-c-k-c0x00ffffff-no-rj-mo",
            "subscribers": 19800,
            "verified": false
          },
          "topSongs": [
            {
              "videoId": "e3n9Rop7I0U",
              "title": "The First Altcoin: Why Is It Still Around Today? (Litecoin)",
              "views": 3666,
              "duration": "11:09",
              "thumbnail": "https://i.ytimg.com/vi/e3n9Rop7I0U/hq720.jpg"
            },
            {
              "videoId": "s8tSVaWt-U0",
              "title": "Litecoin Creator On 2026’s Big Moves In Crypto | Charlie Lee",
              "views": 12581,
              "duration": "39:58",
              "thumbnail": "https://i.ytimg.com/vi/s8tSVaWt-U0/hq720.jpg"
            },
            {
              "videoId": "JMTJvXyHJGU",
              "title": "What is Litecoin? LTC Explained with Animations",
              "views": 148770,
              "duration": "7:40",
              "thumbnail": "https://i.ytimg.com/vi/JMTJvXyHJGU/hq720.jpg"
            },
            {
              "videoId": "pMRMujSLhOc",
              "title": "2026 Litecoin LTC Millionaire Investment Playbook",
              "views": 357,
              "duration": "8:04",
              "thumbnail": "https://i.ytimg.com/vi/pMRMujSLhOc/hqdefault.jpg"
            },
            {
              "videoId": "k0o1kcRyTBo",
              "title": "Litecoin LTC $4,500-$6,300 Price Prediction: Is LTC the Next ZEC??",
              "views": 2743,
              "duration": "11:42",
              "thumbnail": "https://i.ytimg.com/vi/k0o1kcRyTBo/hq720.jpg"
            }
          ],
          "songCount": 5
        },
        {
          "name": "Les Pretres",
          "channel": {
            "id": "UC9XQq1hnr7sFdWwkSrOT6dA",
            "name": "Les Prêtres Orthodoxes - Topic",
            "image": "https://yt3.ggpht.com/CQH38c-1QTM7opAp6xQkoXBHd03w7Z_NNCLu8MC50fEZBI8KkgXkZhsmX1iKPPXJ_5pMooUGFg=s88-c-k-c0x00ffffff-no-rj-mo",
            "subscribers": 2650,
            "verified": false
          },
          "topSongs": [
            {
              "videoId": "l7Z-kK8DUMs",
              "title": "Les Prêtres - Spiritus Dei (Sarabande)",
              "views": 3698402,
              "duration": "4:15",
              "thumbnail": "https://i.ytimg.com/vi/l7Z-kK8DUMs/hq720.jpg"
            },
            {
              "videoId": "dlLlYnzNIJg",
              "title": "LES PRÊTRES  Glorificamus te (Le Lac des Cygnes)",
              "views": 1067536,
              "duration": "3:37",
              "thumbnail": "https://i.ytimg.com/vi/dlLlYnzNIJg/hqdefault.jpg"
            },
            {
              "videoId": "TVYBGcofhjU",
              "title": "Puisque Tu Pars - Les Prêtres",
              "views": 14735608,
              "duration": "5:02",
              "thumbnail": "https://i.ytimg.com/vi/TVYBGcofhjU/hq720.jpg"
            },
            {
              "videoId": "nE4tyjBTk8Y",
              "title": "Les Prêtres -- Savoir Aimer",
              "views": 897566,
              "duration": "4:02",
              "thumbnail": "https://i.ytimg.com/vi/nE4tyjBTk8Y/hq720.jpg"
            },
            {
              "videoId": "Hn8roMGbT-0",
              "title": "Les prêtres (Gloria)",
              "views": 126378,
              "duration": "56:02",
              "thumbnail": "https://i.ytimg.com/vi/Hn8roMGbT-0/hqdefault.jpg"
            }
          ],
          "songCount": 5
        },
        {
          "name": "Maggie Blanchard",
          "channel": {
            "id": "UC0mEneGOejVMZ5UZ6s6quoQ",
            "name": "Maggie Blanchard - Topic",
            "image": "https://yt3.ggpht.com/K-RyPzvlzXjxwYImf5e4CpBewZaa_UFjBPW8juPy9iaQjsqvgkl2qvdWfXmxXaa7AietfJpa=s88-c-k-c0x00ffffff-no-rj-mo",
            "subscribers": 44400,
            "verified": false
          },
          "topSongs": [
            {
              "videoId": "4HMaewnClGE",
              "title": "Maggie Blanchard - Libéré",
              "views": 5083514,
              "duration": "5:05",
              "thumbnail": "https://i.ytimg.com/vi/4HMaewnClGE/hqdefault.jpg"
            },
            {
              "videoId": "uPD_6tLj588",
              "title": "Maggie Blanchard - Compilation de louanges",
              "views": 647866,
              "duration": "1:51:27",
              "thumbnail": "https://i.ytimg.com/vi/uPD_6tLj588/hqdefault.jpg"
            },
            {
              "videoId": "iy9OKdiOCZQ",
              "title": "Quand je regarde ta sainteté",
              "views": 7738476,
              "duration": "7:07",
              "thumbnail": "https://i.ytimg.com/vi/iy9OKdiOCZQ/hq720.jpg"
            },
            {
              "videoId": "_szL0TK1t9U",
              "title": "Personne ne peut t'aimer",
              "views": 562979,
              "duration": "6:16",
              "thumbnail": "https://i.ytimg.com/vi/_szL0TK1t9U/hq720.jpg"
            },
            {
              "videoId": "9ihmdGYKmp8",
              "title": "Pour tout ce que tu es",
              "views": 1669922,
              "duration": "6:22",
              "thumbnail": "https://i.ytimg.com/vi/9ihmdGYKmp8/hq720.jpg"
            }
          ],
          "songCount": 5
        },
        {
          "name": "Marcel Boungou",
          "channel": {},
          "topSongs": [
            {
              "videoId": "aNL4VlDL57k",
              "title": "Je veux me réjouir dans le Dieu de mon Salut-Marcel BOUNGOU",
              "views": 13590269,
              "duration": "8:32",
              "thumbnail": "https://i.ytimg.com/vi/aNL4VlDL57k/hqdefault.jpg"
            },
            {
              "videoId": "C7Hv3QM3bdE",
              "title": "Marcel BOUNGOU - JE SUIS COUVERT - Worship Instant",
              "views": 341984,
              "duration": "4:37",
              "thumbnail": "https://i.ytimg.com/vi/C7Hv3QM3bdE/hqdefault.jpg"
            },
            {
              "videoId": "nSDjrpJoh2s",
              "title": "Total Praise - Je veux me réjouir",
              "views": 405976,
              "duration": "3:36",
              "thumbnail": "https://i.ytimg.com/vi/nSDjrpJoh2s/hqdefault.jpg"
            },
            {
              "videoId": "6CelrGb23p0",
              "title": "Près de toi - Marcel Boungou",
              "views": 675769,
              "duration": "6:09",
              "thumbnail": "https://i.ytimg.com/vi/6CelrGb23p0/hq720.jpg"
            },
            {
              "videoId": "y0B__Xf444I",
              "title": "Je suis couvert",
              "views": 52010,
              "duration": "4:37",
              "thumbnail": "https://i.ytimg.com/vi/y0B__Xf444I/hq720.jpg"
            }
          ],
          "songCount": 5
        },
        {
          "name": "Natasha St-Pier",
          "channel": {
            "id": "UCjnqE1aDtnaqppLQzt8wYMQ",
            "name": "Natasha St-Pier",
            "image": "https://yt3.googleusercontent.com/PILHnClSOTOI2Uga-DcPqT31sz_GcPNg1jvP8U58wPpw6beMmnkDl4azQ4lyKJijjMw_iJIS7eo=s88-c-k-c0x00ffffff-no-rj-mo",
            "subscribers": 258000,
            "verified": true
          },
          "topSongs": [
            {
              "videoId": "yB_UBqMRvKk",
              "title": "Natasha St-Pier - Tu trouveras (Clip officiel)",
              "views": 85335249,
              "duration": "3:49",
              "thumbnail": "https://i.ytimg.com/vi/yB_UBqMRvKk/hq720.jpg"
            },
            {
              "videoId": "cIkkPgsp39o",
              "title": "[HD] Natasha St-Pier - Je N'ai Que Mon Ame",
              "views": 7465416,
              "duration": "2:52",
              "thumbnail": "https://i.ytimg.com/vi/cIkkPgsp39o/hq720.jpg"
            },
            {
              "videoId": "o6Qd6fM1Z48",
              "title": "Vierge Marie",
              "views": 736010,
              "duration": "4:55",
              "thumbnail": "https://i.ytimg.com/vi/o6Qd6fM1Z48/hq720.jpg"
            },
            {
              "videoId": "FBUk6HuoRMY",
              "title": "Vierge Marie  (Natasha St-Pier)",
              "views": 1157068,
              "duration": "4:55",
              "thumbnail": "https://i.ytimg.com/vi/FBUk6HuoRMY/hq720.jpg"
            },
            {
              "videoId": "qZMjiEkT-yA",
              "title": "Natasha St Pier - Un ange frappe a ma porte (Clip officiel)",
              "views": 15761676,
              "duration": "3:35",
              "thumbnail": "https://i.ytimg.com/vi/qZMjiEkT-yA/hq720.jpg"
            }
          ],
          "songCount": 5
        },
        {
          "name": "Pierre Nicolas de Katow",
          "channel": {
            "id": "UCu4oiDKnhCjf1b5h-1DEHhw",
            "name": "Pierre Nicolas de Katow - Topic",
            "image": "https://yt3.ggpht.com/h-8s1YOKhlIqEoiUZfB_lds5Aj-uoaG2xXeZ6HkRja0lwG69WVfWAb9RgtIWaCWe86e5ErhvAQ=s88-c-k-c0x00ffffff-no-rj-mo",
            "subscribers": 554,
            "verified": false
          },
          "topSongs": [
            {
              "videoId": "5u1JAFzRLLY",
              "title": "Pierre-Nicolas De Katow - Te connaître",
              "views": 11315,
              "duration": "4:40",
              "thumbnail": "https://i.ytimg.com/vi/5u1JAFzRLLY/hq720.jpg"
            },
            {
              "videoId": "GSi6mBOsvP4",
              "title": "FWU #12 - Pierre-Nicolas De Katow / L’amour de notre père (Samuel Olivier)",
              "views": 853,
              "duration": "3:09",
              "thumbnail": "https://i.ytimg.com/vi/GSi6mBOsvP4/hq720.jpg"
            },
            {
              "videoId": "a_1OT6Louuw",
              "title": "Un chant nouveau monte - Pierre-Nicolas de Katow",
              "views": 3668,
              "duration": "4:24",
              "thumbnail": "https://i.ytimg.com/vi/a_1OT6Louuw/hq720.jpg"
            },
            {
              "videoId": "KkiNA8oXg60",
              "title": "Ta Parole (Amen)",
              "views": 13240,
              "duration": "4:14",
              "thumbnail": "https://i.ytimg.com/vi/KkiNA8oXg60/hq720.jpg"
            },
            {
              "videoId": "so8LtcH64ig",
              "title": "Esprit du Dieu vivant",
              "views": 864,
              "duration": "5:14",
              "thumbnail": "https://i.ytimg.com/vi/so8LtcH64ig/hq720.jpg"
            }
          ],
          "songCount": 5
        },
        {
          "name": "Sebastien Demrey",
          "channel": {
            "id": "UCpEdy9PAgeVvyrP31fZ1f5A",
            "name": "Sebastian Demrey",
            "image": "https://yt3.googleusercontent.com/ytc/AIdro_nQdA1Uro7j1EI3HarWESaqZXXmG2u2js_JS7rnPDVFYNQ=s88-c-k-c0x00ffffff-no-rj-mo",
            "subscribers": 91500,
            "verified": false
          },
          "topSongs": [
            {
              "videoId": "mywV4B6SYGE",
              "title": "COMPTE LES BIENFAITS  (Fast Forward Session) Sebastian Demrey & Jimmy Lahaie",
              "views": 3896801,
              "duration": "4:09",
              "thumbnail": "https://i.ytimg.com/vi/mywV4B6SYGE/hq720.jpg"
            },
            {
              "videoId": "KlJr6WYga2w",
              "title": "Bénis l'Éternel ft. Sebastian Demrey, Le nom du Seigneur, Tu es grand Seigneur | Medley de louange",
              "views": 385592,
              "duration": "14:06",
              "thumbnail": "https://i.ytimg.com/vi/KlJr6WYga2w/hq720.jpg"
            },
            {
              "videoId": "bGD-zY1Z7vQ",
              "title": "DIEU TOUT-PUISSANT (chorale 5000 voix) Sebastian Demrey & Jimmy Lahaie",
              "views": 5683593,
              "duration": "7:41",
              "thumbnail": "https://i.ytimg.com/vi/bGD-zY1Z7vQ/hq720.jpg"
            },
            {
              "videoId": "ik-NfXy4DUw",
              "title": "Seigneur à quel autre / Parce qu'il vit - Sebastian Demrey & Jimmy Lahaie",
              "views": 466393,
              "duration": "5:10",
              "thumbnail": "https://i.ytimg.com/vi/ik-NfXy4DUw/hq720.jpg"
            },
            {
              "videoId": "hX_S-xGvw28",
              "title": "LA VOIX DU SEIGNEUR M'APPELLE - Sebastian Demrey & Jimmy Lahaie (featuring Andrée Grise)",
              "views": 1622469,
              "duration": "4:04",
              "thumbnail": "https://i.ytimg.com/vi/hX_S-xGvw28/hq720.jpg"
            }
          ],
          "songCount": 5
        }
      ]
    }
  }
}