{"status":true,"data":[{"type":"video","videoId":"iyk8fkFXluw","url":"https://youtube.com/watch?v=iyk8fkFXluw","title":"louange orphey feat archevêque Kodja Guy Vincent","description":"Dieu veut benir.","image":"https://i.ytimg.com/vi/iyk8fkFXluw/hqdefault.jpg","thumbnail":"https://i.ytimg.com/vi/iyk8fkFXluw/hqdefault.jpg","seconds":488,"timestamp":"8:08","duration":{"seconds":488,"timestamp":"8:08"},"ago":"4 years ago","views":79353,"author":{"name":"natoushka kibib","url":"https://youtube.com/@natoushkakibib3569"}},{"type":"video","videoId":"Hxh7T7hUUVQ","url":"https://youtube.com/watch?v=Hxh7T7hUUVQ","title":"grace divine ft Bishop Kodja","description":"","image":"https://i.ytimg.com/vi/Hxh7T7hUUVQ/hqdefault.jpg","thumbnail":"https://i.ytimg.com/vi/Hxh7T7hUUVQ/hqdefault.jpg","seconds":385,"timestamp":"6:25","duration":{"seconds":385,"timestamp":"6:25"},"ago":"9 years ago","views":60417,"author":{"name":"Emekah Godwin (Godwin)","url":"https://youtube.com/@emekahgodwin3565"}},{"type":"video","videoId":"IAWCAXmBMyE","url":"https://youtube.com/watch?v=IAWCAXmBMyE","title":"Dieu qui garde L'Alliance interprété par l'Archevêque Kodja Guy Vincent et le chantre Orphey 🙏🏼🙇🏽‍♀️","description":"Vidéo de Natoushka Kibib.","image":"https://i.ytimg.com/vi/IAWCAXmBMyE/hqdefault.jpg","thumbnail":"https://i.ytimg.com/vi/IAWCAXmBMyE/hqdefault.jpg","seconds":121,"timestamp":"2:01","duration":{"seconds":121,"timestamp":"2:01"},"ago":"5 years ago","views":168388,"author":{"name":"natoushka kibib","url":"https://youtube.com/@natoushkakibib3569"}},{"type":"video","videoId":"BT7PP3dywms","url":"https://youtube.com/watch?v=BT7PP3dywms","title":"Archevêque Kodja - Comment gagner tous ses combats par le silence ?","description":"Archevêque Kodja - Comment gagner tous ses combats par le silence ?","image":"https://i.ytimg.com/vi/BT7PP3dywms/hq720.jpg","thumbnail":"https://i.ytimg.com/vi/BT7PP3dywms/hq720.jpg","seconds":4093,"timestamp":"1:08:13","duration":{"seconds":4093,"timestamp":"1:08:13"},"ago":"8 months ago","views":14965,"author":{"name":"MEG-VIE TV","url":"https://youtube.com/@MEG-VIETV"}},{"type":"video","videoId":"MGrPSFsI_oY","url":"https://youtube.com/watch?v=MGrPSFsI_oY","title":"C'est la fin qui compte avec l'archevêque Kodja Guy Vincent","description":"","image":"https://i.ytimg.com/vi/MGrPSFsI_oY/hqdefault.jpg","thumbnail":"https://i.ytimg.com/vi/MGrPSFsI_oY/hqdefault.jpg","seconds":45,"timestamp":"0:45","duration":{"seconds":45,"timestamp":"0:45"},"ago":"7 years ago","views":6005,"author":{"name":"natoushka kibib","url":"https://youtube.com/@natoushkakibib3569"}},{"type":"video","videoId":"hHnr80h2smM","url":"https://youtube.com/watch?v=hHnr80h2smM","title":"louange à l'ivoirienne archevêque Kodja Guy Vincent","description":"avec l'archevêque Kodja Guy Vincent.","image":"https://i.ytimg.com/vi/hHnr80h2smM/hqdefault.jpg","thumbnail":"https://i.ytimg.com/vi/hHnr80h2smM/hqdefault.jpg","seconds":872,"timestamp":"14:32","duration":{"seconds":872,"timestamp":"14:32"},"ago":"5 years ago","views":38547,"author":{"name":"natoushka kibib","url":"https://youtube.com/@natoushkakibib3569"}},{"type":"video","videoId":"w05k7BhqY-U","url":"https://youtube.com/watch?v=w05k7BhqY-U","title":"ARCHEVÊQUE KODJA GUY VINCENT feat CHANTRE ORPHEY ( dit merci à JÉSUS)","description":"louange adoration.","image":"https://i.ytimg.com/vi/w05k7BhqY-U/hqdefault.jpg","thumbnail":"https://i.ytimg.com/vi/w05k7BhqY-U/hqdefault.jpg","seconds":239,"timestamp":"3:59","duration":{"seconds":239,"timestamp":"3:59"},"ago":"4 years ago","views":14510,"author":{"name":"natoushka kibib","url":"https://youtube.com/@natoushkakibib3569"}},{"type":"video","videoId":"OVJHMJ383QI","url":"https://youtube.com/watch?v=OVJHMJ383QI","title":"QR LIVE AVEC ARCHEVÊQUE KODJA","description":"QR LIVE Thème : Récemment, des statistiques ont révélé plus de 1700 cas de divorce en milieu chrétien. Une situation qui ...","image":"https://i.ytimg.com/vi/OVJHMJ383QI/hq720.jpg","thumbnail":"https://i.ytimg.com/vi/OVJHMJ383QI/hq720.jpg","seconds":5527,"timestamp":"1:32:07","duration":{"seconds":5527,"timestamp":"1:32:07"},"ago":"Streamed 2 months ago","views":921,"author":{"name":"MEG-VIE TV","url":"https://youtube.com/@MEG-VIETV"}},{"type":"video","videoId":"LjFkxGrLCEs","url":"https://youtube.com/watch?v=LjFkxGrLCEs","title":"Adoration avec Archevêque Kodja Guy Vincent","description":"","image":"https://i.ytimg.com/vi/LjFkxGrLCEs/hqdefault.jpg","thumbnail":"https://i.ytimg.com/vi/LjFkxGrLCEs/hqdefault.jpg","seconds":244,"timestamp":"4:04","duration":{"seconds":244,"timestamp":"4:04"},"ago":"7 years ago","views":11442,"author":{"name":"natoushka kibib","url":"https://youtube.com/@natoushkakibib3569"}},{"type":"video","videoId":"hJluVYqMH0s","url":"https://youtube.com/watch?v=hJluVYqMH0s","title":"louange avec l'archevêque Kodja Guy Vincent🙏🏼❤🙏🏼","description":"conduit moi par la main etc...","image":"https://i.ytimg.com/vi/hJluVYqMH0s/hqdefault.jpg","thumbnail":"https://i.ytimg.com/vi/hJluVYqMH0s/hqdefault.jpg","seconds":904,"timestamp":"15:04","duration":{"seconds":904,"timestamp":"15:04"},"ago":"4 years ago","views":57048,"author":{"name":"natoushka kibib","url":"https://youtube.com/@natoushkakibib3569"}},{"type":"video","videoId":"yxGv7BzbN8E","url":"https://youtube.com/watch?v=yxGv7BzbN8E","title":"Archevêque Kodja - Les principes de la richesse durable","description":"Archevêque Kodja - Les principes de la richesse durable.","image":"https://i.ytimg.com/vi/yxGv7BzbN8E/hq720.jpg","thumbnail":"https://i.ytimg.com/vi/yxGv7BzbN8E/hq720.jpg","seconds":3517,"timestamp":"58:37","duration":{"seconds":3517,"timestamp":"58:37"},"ago":"7 months ago","views":6849,"author":{"name":"MEG-VIE TV","url":"https://youtube.com/@MEG-VIETV"}},{"type":"video","videoId":"eQV7Om3PmUo","url":"https://youtube.com/watch?v=eQV7Om3PmUo","title":"L'ARCHEVÈQUE GUY-VINCENT KODJA \" À 7 ans je prêchais déjà \"","description":"Il a commencé dans l'ombre… aujourd'hui, beaucoup l'écoutent. L'Archevêque Guy Vincent se livre comme rarement dans THE ...","image":"https://i.ytimg.com/vi/eQV7Om3PmUo/hq720.jpg","thumbnail":"https://i.ytimg.com/vi/eQV7Om3PmUo/hq720.jpg","seconds":5359,"timestamp":"1:29:19","duration":{"seconds":5359,"timestamp":"1:29:19"},"ago":"2 months ago","views":42257,"author":{"name":"YvideroShow","url":"https://youtube.com/@Yvideroshow"}},{"type":"live","videoId":"mGcVUqSiIGI","url":"https://youtube.com/watch?v=mGcVUqSiIGI","title":"Archevêque Kodja - Les principes de la richesse durable (2)","description":"Archevêque Kodja - Les principes de la richesse durable (2) Sous-thème : L'intégrité, L'honnêteté et la bonne réputation.Archevêque KODJA- COMMENT REMPORTER LA PLUS GRANDE BATAILLE DE SA VIE ET VIVRE LE ROYAUME?(Partie 3)Archevêque Kodja - Tel un homme pense tel il est ou la pensée de celui qui est destinée.Archevêque Kodja - LA VIE DU JEUNE CHRETIEN DYNAMIQUE.Lifetv.Archevêque Kodja - Les quatre piliers de la réussite. Sous thème 3 : La Négligence.sanogo #castanou #tunasi #tala Disclaimer: Please understand that the videos on this channel fall under the remits of Fair Use, ...In this inspired video, Father Bienvenu Djea immerses us in the heart of life in the Holy Spirit, exploring the richness of ...Dimanche 24 mai à 21h (heure de Paris), suivez-nous EN LIVE à distance, pour la SESSION 5 de la conférence Pentecôte 2026 !","image":"https://i.ytimg.com/vi/mGcVUqSiIGI/hq720.jpg","thumbnail":"https://i.ytimg.com/vi/mGcVUqSiIGI/hq720.jpg","watching":16195,"author":{"name":"MEG-VIE TV","url":"https://youtube.com/@MEG-VIETV"},"status":"LIVE"},{"type":"list","listId":"PLbizYW5kLgCIZlV7cqiK1igcCrsaWkNWo","url":"https://youtube.com/playlist?list=PLbizYW5kLgCIZlV7cqiK1igcCrsaWkNWo","title":"louange reveran guy kodja","image":"https://i.ytimg.com/vi/hJluVYqMH0s/hqdefault.jpg","thumbnail":"https://i.ytimg.com/vi/hJluVYqMH0s/hqdefault.jpg","videoCount":24,"author":{"name":"Kouassi Jean Paul Kouame","url":"https://youtube.com/@kouassijeanpaulkouame3862"}},{"type":"video","videoId":"y9ncB3f1pbI","url":"https://youtube.com/watch?v=y9ncB3f1pbI","title":"Archevêque KODJA- COMMENT REMPORTER LA PLUS GRANDE BATAILLE DE SA VIE ET VIVRE LE ROYAUME?(Partie1)","description":"Archevêque KODJA- COMMENT REMPORTER LA PLUS GRANDE BATAILLE DE SA VIE ET VIVRE LE ROYAUME? PARTIE 1.","image":"https://i.ytimg.com/vi/y9ncB3f1pbI/hq720.jpg","thumbnail":"https://i.ytimg.com/vi/y9ncB3f1pbI/hq720.jpg","seconds":3713,"timestamp":"1:01:53","duration":{"seconds":3713,"timestamp":"1:01:53"},"ago":"2 months ago","views":4301,"author":{"name":"MEG-VIE TV","url":"https://youtube.com/@MEG-VIETV"}},{"type":"video","videoId":"9tuoGZk7aH8","url":"https://youtube.com/watch?v=9tuoGZk7aH8","title":"ARCHEVEQUE KODJA GUY VINCENT- CA NE TE REGARDE PAS...","description":"L'homme de Dieu parle ici de plusieurs aspects très importants. Le père (pasteur) doit couvrir et protéger son fils vice-versa.","image":"https://i.ytimg.com/vi/9tuoGZk7aH8/hqdefault.jpg","thumbnail":"https://i.ytimg.com/vi/9tuoGZk7aH8/hqdefault.jpg","seconds":1497,"timestamp":"24:57","duration":{"seconds":1497,"timestamp":"24:57"},"ago":"10 years ago","views":5081,"author":{"name":"Plus Que Vainqueur","url":"https://youtube.com/@PlusQueVainqueurTV"}},{"type":"video","videoId":"Ka9eeMi_3ew","url":"https://youtube.com/watch?v=Ka9eeMi_3ew","title":"Aqolopa | KODJA Guy Vincent ft. Dezy Champion","description":"Découvre Aqolopa, interprété par KODJA Guy Vincent ft. Dezy Champion, un puissant moment de louange et d'adoration qui ...","image":"https://i.ytimg.com/vi/Ka9eeMi_3ew/hqdefault.jpg","thumbnail":"https://i.ytimg.com/vi/Ka9eeMi_3ew/hqdefault.jpg","seconds":363,"timestamp":"6:03","duration":{"seconds":363,"timestamp":"6:03"},"ago":"1 year ago","views":91568,"author":{"name":"Bøšha 👁🦅 Qweezy","url":"https://youtube.com/@LeNouvelAvenir"}},{"type":"video","videoId":"6U5LZ0CBtxk","url":"https://youtube.com/watch?v=6U5LZ0CBtxk","title":"Archevêque Kodja - Les quatre piliers de la réussite. Sous thème 2 : La Discrétion","description":"Archevêque Kodja - Les quatre piliers de la réussite. Sous thème 2 : La Discrétion.","image":"https://i.ytimg.com/vi/6U5LZ0CBtxk/hq720.jpg","thumbnail":"https://i.ytimg.com/vi/6U5LZ0CBtxk/hq720.jpg","seconds":3812,"timestamp":"1:03:32","duration":{"seconds":3812,"timestamp":"1:03:32"},"ago":"1 year ago","views":10723,"author":{"name":"MEG-VIE TV","url":"https://youtube.com/@MEG-VIETV"}},{"type":"video","videoId":"ygMr1f2m3ZU","url":"https://youtube.com/watch?v=ygMr1f2m3ZU","title":"Louange avec Bishop Kodja Guy Vincent | Moment de louange","description":"Vivez un puissant moment de louange avec Bishop Kodja Guy Vincent Que ce temps dans la présence de Dieu fortifie votre ...","image":"https://i.ytimg.com/vi/ygMr1f2m3ZU/hqdefault.jpg","thumbnail":"https://i.ytimg.com/vi/ygMr1f2m3ZU/hqdefault.jpg","seconds":552,"timestamp":"9:12","duration":{"seconds":552,"timestamp":"9:12"},"ago":"1 month ago","views":133,"author":{"name":"Bøšha 👁🦅 Qweezy","url":"https://youtube.com/@LeNouvelAvenir"}},{"type":"video","videoId":"cU0Z6DXCtvo","url":"https://youtube.com/watch?v=cU0Z6DXCtvo","title":"Archevêque KODJA - La puissance de la parole","description":"Archevêque KODJA - La puissance de la parole.","image":"https://i.ytimg.com/vi/cU0Z6DXCtvo/hq720.jpg","thumbnail":"https://i.ytimg.com/vi/cU0Z6DXCtvo/hq720.jpg","seconds":3993,"timestamp":"1:06:33","duration":{"seconds":3993,"timestamp":"1:06:33"},"ago":"1 month ago","views":3262,"author":{"name":"MEG-VIE TV","url":"https://youtube.com/@MEG-VIETV"}},{"type":"video","videoId":"LEdZrQVmtJA","url":"https://youtube.com/watch?v=LEdZrQVmtJA","title":"Adoration archevêque Kodja Guy Vincent et le chantre orphey","description":"","image":"https://i.ytimg.com/vi/LEdZrQVmtJA/hqdefault.jpg","thumbnail":"https://i.ytimg.com/vi/LEdZrQVmtJA/hqdefault.jpg","seconds":167,"timestamp":"2:47","duration":{"seconds":167,"timestamp":"2:47"},"ago":"7 years ago","views":26314,"author":{"name":"natoushka kibib","url":"https://youtube.com/@natoushkakibib3569"}},{"type":"live","videoId":"iHxh5LpqRRg","url":"https://youtube.com/watch?v=iHxh5LpqRRg","title":"louange orphey feat archevêque Kodja Guy Vincent","description":"Dieu veut benir.Vidéo de Natoushka Kibib.Archevêque Kodja - Comment gagner tous ses combats par le silence ?avec l'archevêque Kodja Guy Vincent.louange adoration.QR LIVE Thème : Récemment, des statistiques ont révélé plus de 1700 cas de divorce en milieu chrétien. Une situation qui ...conduit moi par la main etc...Archevêque Kodja - Les principes de la richesse durable.Il a commencé dans l'ombre… aujourd'hui, beaucoup l'écoutent. L'Archevêque Guy Vincent se livre comme rarement dans THE ...Archevêque Kodja - Les principes de la richesse durable (2) Sous-thème : L'intégrité, L'honnêteté et la bonne réputation.Archevêque KODJA- COMMENT REMPORTER LA PLUS GRANDE BATAILLE DE SA VIE ET VIVRE LE ROYAUME?(Partie 3)Archevêque Kodja - Tel un homme pense tel il est ou la pensée de celui qui est destinée.Archevêque Kodja - LA VIE DU JEUNE CHRETIEN DYNAMIQUE.Lifetv.Archevêque Kodja - Les quatre piliers de la réussite. Sous thème 3 : La Négligence.sanogo #castanou #tunasi #tala Disclaimer: Please understand that the videos on this channel fall under the remits of Fair Use, ...In this inspired video, Father Bienvenu Djea immerses us in the heart of life in the Holy Spirit, exploring the richness of ...Dimanche 24 mai à 21h (heure de Paris), suivez-nous EN LIVE à distance, pour la SESSION 5 de la conférence Pentecôte 2026 !Archevêque KODJA- COMMENT REMPORTER LA PLUS GRANDE BATAILLE DE SA VIE ET VIVRE LE ROYAUME? PARTIE 1.L'homme de Dieu parle ici de plusieurs aspects très importants. Le père (pasteur) doit couvrir et protéger son fils vice-versa.Découvre Aqolopa, interprété par KODJA Guy Vincent ft. Dezy Champion, un puissant moment de louange et d'adoration qui ...Archevêque Kodja - Les quatre piliers de la réussite. Sous thème 2 : La Discrétion.Vivez un puissant moment de louange avec Bishop Kodja Guy Vincent Que ce temps dans la présence de Dieu fortifie votre ...Archevêque KODJA - La puissance de la parole.","image":"https://i.ytimg.com/vi/iHxh5LpqRRg/frame0.jpg","thumbnail":"https://i.ytimg.com/vi/iHxh5LpqRRg/frame0.jpg","watching":16195,"author":{"name":"natoushka kibib","url":"https://youtube.com/@natoushkakibib3569"},"status":"LIVE"}],"timestamp":"2026-05-24T20:44:36.411Z"}