{"status":true,"data":[{"type":"channel","name":"Faye Wong Official Channel 王菲 官方頻道","url":"https://youtube.com/@fayewongofficialchannel560","baseUrl":"/@fayewongofficialchannel560","id":"UCos8gkwQivJ_hHeoCcs6yXg","title":"Faye Wong Official Channel 王菲 官方頻道","about":"Faye Wong Official Channel.","image":"https://yt3.ggpht.com/ytc/AIdro_lAHND2trPOwZt7grMgPw8yUq9r-gJWf9046V3rm9Y6TGE=s88-c-k-c0x00ffffff-no-rj-mo","thumbnail":"https://yt3.ggpht.com/ytc/AIdro_lAHND2trPOwZt7grMgPw8yUq9r-gJWf9046V3rm9Y6TGE=s88-c-k-c0x00ffffff-no-rj-mo","videoCount":-1,"videoCountLabel":"-1","verified":true,"subCount":201000,"subCountLabel":"201K"},{"type":"video","videoId":"hN2jOHeI5tc","url":"https://youtube.com/watch?v=hN2jOHeI5tc","title":"王菲 Faye Wong -《夢中人》(Official Music Video) [HD]","description":"流浪的紅舞鞋(MV 1080pHD/高清)：https://youtu.be/FkgKDzshYSI?si=XS7_J9ZEKtuDs3OV 色盲(MV 1080pHD/ ...","image":"https://i.ytimg.com/vi/hN2jOHeI5tc/hq720.jpg","thumbnail":"https://i.ytimg.com/vi/hN2jOHeI5tc/hq720.jpg","seconds":263,"timestamp":"4:23","duration":{"seconds":263,"timestamp":"4:23"},"ago":"6 years ago","views":1177880,"author":{"name":"FayeWongVEVO","url":"https://youtube.com/@FayeWongOfficial"}},{"type":"video","videoId":"ysObDhmM_84","url":"https://youtube.com/watch?v=ysObDhmM_84","title":"如愿--As wished--王菲--Faye Wong--Pinyin Lyrics","description":"","image":"https://i.ytimg.com/vi/ysObDhmM_84/hqdefault.jpg","thumbnail":"https://i.ytimg.com/vi/ysObDhmM_84/hqdefault.jpg","seconds":264,"timestamp":"4:24","duration":{"seconds":264,"timestamp":"4:24"},"ago":"4 years ago","views":5460273,"author":{"name":"李不语","url":"https://youtube.com/@%E6%9D%8E%E4%B8%8D%E8%AF%AD"}},{"type":"video","videoId":"ZoJCN0pV7Qs","url":"https://youtube.com/watch?v=ZoJCN0pV7Qs","title":"如愿","description":"電影「我和我的父輩」主題曲演唱: 王菲Label：KC Digital Ltd. 作詞: 唐恬OP：北京梦织音传媒有限公司作曲: 錢雷OP：索尼音乐 ...","image":"https://i.ytimg.com/vi/ZoJCN0pV7Qs/hq720.jpg","thumbnail":"https://i.ytimg.com/vi/ZoJCN0pV7Qs/hq720.jpg","seconds":266,"timestamp":"4:26","duration":{"seconds":266,"timestamp":"4:26"},"ago":"4 years ago","views":9053596,"author":{"name":"Faye Wong Official Channel 王菲 官方頻道","url":"https://youtube.com/channel/UCos8gkwQivJ_hHeoCcs6yXg"}},{"type":"video","videoId":"LffTkRuB7z0","url":"https://youtube.com/watch?v=LffTkRuB7z0","title":"王菲时隔七年再登春晚 新歌《世界赠予我的》太好听了！「2025央视春晚」| CCTV春晚","description":"歌曲《世界赠予我的》，演唱：王菲。 【订阅CCTV春晚官方频道】：https://www.youtube.com/@CCTVGala 中央广播电视总 ...","image":"https://i.ytimg.com/vi/LffTkRuB7z0/hq720.jpg","thumbnail":"https://i.ytimg.com/vi/LffTkRuB7z0/hq720.jpg","seconds":238,"timestamp":"3:58","duration":{"seconds":238,"timestamp":"3:58"},"ago":"1 year ago","views":5014799,"author":{"name":"CCTV春晚","url":"https://youtube.com/@CCTVGala"}},{"type":"list","listId":"PLI6kLIhBBwmRDrdO5OZ_JikF9cC3BHOzt","url":"https://youtube.com/playlist?list=PLI6kLIhBBwmRDrdO5OZ_JikF9cC3BHOzt","title":"王菲 Faye Wong - 天空 Tian Kong (Sky) (Full Album)","image":"https://i.ytimg.com/vi/M1uGzE7NfAI/hq720.jpg","thumbnail":"https://i.ytimg.com/vi/M1uGzE7NfAI/hq720.jpg","videoCount":10,"author":{"name":"Mica Medusa","url":"https://youtube.com/@mica_medusa"}},{"type":"video","videoId":"adsrNFdIxLg","url":"https://youtube.com/watch?v=adsrNFdIxLg","title":"王菲 Faye Wong《主角》電視劇同名主題曲 (Official MV)","description":"王菲獻唱張藝謀監製電視劇《主角》 ℗ 2026 KC Digital Ltd. 歌曲《主角》由王菲傾情獻唱，賴婷作詞，范煒作曲。大幕拉開，一戲 ...","image":"https://i.ytimg.com/vi/adsrNFdIxLg/hq720.jpg","thumbnail":"https://i.ytimg.com/vi/adsrNFdIxLg/hq720.jpg","seconds":285,"timestamp":"4:45","duration":{"seconds":285,"timestamp":"4:45"},"ago":"2 weeks ago","views":351459,"author":{"name":"Faye Wong Official Channel 王菲 官方頻道","url":"https://youtube.com/channel/UCos8gkwQivJ_hHeoCcs6yXg"}},{"type":"video","videoId":"XUYdKPqm2cE","url":"https://youtube.com/watch?v=XUYdKPqm2cE","title":"Top Chinese Songs - Faye Wong 王菲 精選好歌 Vol. 1","description":"Hope you enjoy the music. Please help share, like and subscribe.","image":"https://i.ytimg.com/vi/XUYdKPqm2cE/hqdefault.jpg","thumbnail":"https://i.ytimg.com/vi/XUYdKPqm2cE/hqdefault.jpg","seconds":5555,"timestamp":"1:32:35","duration":{"seconds":5555,"timestamp":"1:32:35"},"ago":"3 years ago","views":666223,"author":{"name":"Ali Panda Music","url":"https://youtube.com/@alipandamusic9116"}},{"type":"video","videoId":"iYqhHM19He0","url":"https://youtube.com/watch?v=iYqhHM19He0","title":"王菲 Faye Wong - 知己知彼 (Official Music Video)","description":"收錄於1994 年專輯《胡思亂想》 https://www.youtube.com/playlist?list=OLAK5uy_n67FdQZbg_BdabxrRjKK-XbfUQceGGKD8 ...","image":"https://i.ytimg.com/vi/iYqhHM19He0/hq720.jpg","thumbnail":"https://i.ytimg.com/vi/iYqhHM19He0/hq720.jpg","seconds":215,"timestamp":"3:35","duration":{"seconds":215,"timestamp":"3:35"},"ago":"5 years ago","views":92918,"author":{"name":"Faye Wong Official Channel 王菲 官方頻道","url":"https://youtube.com/channel/UCos8gkwQivJ_hHeoCcs6yXg"}},{"type":"video","videoId":"KDGMU6sdVBE","url":"https://youtube.com/watch?v=KDGMU6sdVBE","title":"Final Fantasy VIII (eyes on me By faye wong)","description":"final fantasy VIII (8) video almost a love story how Squall Leonhart Rinoa Heartilly fall in love, with some video of faye wong ...","image":"https://i.ytimg.com/vi/KDGMU6sdVBE/hqdefault.jpg","thumbnail":"https://i.ytimg.com/vi/KDGMU6sdVBE/hqdefault.jpg","seconds":343,"timestamp":"5:43","duration":{"seconds":343,"timestamp":"5:43"},"ago":"19 years ago","views":15177937,"author":{"name":"wolfking1981","url":"https://youtube.com/@wolfking1981"}},{"type":"video","videoId":"kwvZHMU0cTw","url":"https://youtube.com/watch?v=kwvZHMU0cTw","title":"如愿 Ru Yuan - 王菲 Faye Wong (Lirik & Terjemahan Indonesia)","description":"RuYuan #如愿#FayeWong #王菲.","image":"https://i.ytimg.com/vi/kwvZHMU0cTw/hq720.jpg","thumbnail":"https://i.ytimg.com/vi/kwvZHMU0cTw/hq720.jpg","seconds":263,"timestamp":"4:23","duration":{"seconds":263,"timestamp":"4:23"},"ago":"1 year ago","views":755018,"author":{"name":"Yipedia Songs","url":"https://youtube.com/@YipediaSongs"}},{"type":"video","videoId":"CwwQvC_JiN4","url":"https://youtube.com/watch?v=CwwQvC_JiN4","title":"世界赠予我的","description":"《世界赠予我的》 演唱：王菲作词：袁晶作曲：曹正杰有人放烟花有人追晚风借一缕时光捧一片星空停一停等一等别匆匆造梦者造了 ...","image":"https://i.ytimg.com/vi/CwwQvC_JiN4/hqdefault.jpg","thumbnail":"https://i.ytimg.com/vi/CwwQvC_JiN4/hqdefault.jpg","seconds":233,"timestamp":"3:53","duration":{"seconds":233,"timestamp":"3:53"},"ago":"1 year ago","views":2662067,"author":{"name":"Faye Wong Official Channel 王菲 官方頻道","url":"https://youtube.com/channel/UCos8gkwQivJ_hHeoCcs6yXg"}},{"type":"video","videoId":"tDw_ULjZWA8","url":"https://youtube.com/watch?v=tDw_ULjZWA8","title":"王菲 - 容易受傷的女人 (粵語版) (Official Music Video)","description":"... 歌手：王菲歌曲：容易受傷的女人專輯：Coming Home 發行日期：1992年8月13日Music video by Faye Wong performing Jung ...","image":"https://i.ytimg.com/vi/tDw_ULjZWA8/hq720.jpg","thumbnail":"https://i.ytimg.com/vi/tDw_ULjZWA8/hq720.jpg","seconds":260,"timestamp":"4:20","duration":{"seconds":260,"timestamp":"4:20"},"ago":"7 years ago","views":2100227,"author":{"name":"FayeWongVEVO","url":"https://youtube.com/@FayeWongOfficial"}},{"type":"video","videoId":"4nQQTm-ALBY","url":"https://youtube.com/watch?v=4nQQTm-ALBY","title":"[HQ]Faye Wong-Heart Sutra 王菲《心经》1小时版本 1 Hour Mind & Soul Meditation Healing Music","description":"希望大家会喜欢聆听这首歌，而且别忘了点阅我的YouTube频道！ Hope you enjoy the music, LIKE and SUBSCRIBE my channel!","image":"https://i.ytimg.com/vi/4nQQTm-ALBY/hq720.jpg","thumbnail":"https://i.ytimg.com/vi/4nQQTm-ALBY/hq720.jpg","seconds":3716,"timestamp":"1:01:56","duration":{"seconds":3716,"timestamp":"1:01:56"},"ago":"6 years ago","views":2198480,"author":{"name":"Raynicck","url":"https://youtube.com/@Raynicck"}},{"type":"video","videoId":"mjuS9shGYhE","url":"https://youtube.com/watch?v=mjuS9shGYhE","title":"王菲 Faye Wong -《流年》(Official Music Video) [HD]","description":"Music video by Faye Wong performing Liú Nián. © 2001 Faye's Music Ltd. 歌手：王菲歌曲：流年專輯：王菲(2001) 發行 ...","image":"https://i.ytimg.com/vi/mjuS9shGYhE/hq720.jpg","thumbnail":"https://i.ytimg.com/vi/mjuS9shGYhE/hq720.jpg","seconds":264,"timestamp":"4:24","duration":{"seconds":264,"timestamp":"4:24"},"ago":"5 years ago","views":288148,"author":{"name":"FayeWongVEVO","url":"https://youtube.com/@FayeWongOfficial"}},{"type":"video","videoId":"tx34QxXzZrg","url":"https://youtube.com/watch?v=tx34QxXzZrg","title":"Faye Wong — 知己知彼 (Cocteau Twins Cover)","description":"Сover of the Сocteau Twins song called \"Know Who You Are At Every Age\"","image":"https://i.ytimg.com/vi/tx34QxXzZrg/hqdefault.jpg","thumbnail":"https://i.ytimg.com/vi/tx34QxXzZrg/hqdefault.jpg","seconds":199,"timestamp":"3:19","duration":{"seconds":199,"timestamp":"3:19"},"ago":"6 years ago","views":83162,"author":{"name":"porupiko","url":"https://youtube.com/@porupiko"}},{"type":"video","videoId":"5wmfXve11rM","url":"https://youtube.com/watch?v=5wmfXve11rM","title":"王菲 - 紅豆","description":"「唱遊」數位下載及試聽Digital download & streaming 【iTunes】 http://goo.gl/CXHynK 【Spotify】http://goo.gl/0MBXvO 【紅豆】 ...","image":"https://i.ytimg.com/vi/5wmfXve11rM/hqdefault.jpg","thumbnail":"https://i.ytimg.com/vi/5wmfXve11rM/hqdefault.jpg","seconds":260,"timestamp":"4:20","duration":{"seconds":260,"timestamp":"4:20"},"ago":"11 years ago","views":50037604,"author":{"name":"Faye Wong Official Channel 王菲 官方頻道","url":"https://youtube.com/channel/UCos8gkwQivJ_hHeoCcs6yXg"}},{"type":"video","videoId":"9IORN1EiPP4","url":"https://youtube.com/watch?v=9IORN1EiPP4","title":"愛與痛的邊緣","description":"Provided to YouTube by Universal Music Group 愛與痛的邊緣· 王菲討好自己℗ 1994 Cinepoly Records Co. Ltd. Released on: ...","image":"https://i.ytimg.com/vi/9IORN1EiPP4/hq720.jpg","thumbnail":"https://i.ytimg.com/vi/9IORN1EiPP4/hq720.jpg","seconds":274,"timestamp":"4:34","duration":{"seconds":274,"timestamp":"4:34"},"views":7066687,"author":{"name":"Faye Wong Official Channel 王菲 官方頻道","url":"https://youtube.com/channel/UCos8gkwQivJ_hHeoCcs6yXg"}},{"type":"video","videoId":"eGxxNltrNvA","url":"https://youtube.com/watch?v=eGxxNltrNvA","title":"王菲 Faye Wong -《愛與痛的邊緣》(Official Music Video)","description":"Music video by Faye Wong performing Oi jyu tung dik binjyun. © 1994 Cinepoly Records Co.,Ltd. 《愛與痛的邊緣》收錄於1994年 ...","image":"https://i.ytimg.com/vi/eGxxNltrNvA/hq720.jpg","thumbnail":"https://i.ytimg.com/vi/eGxxNltrNvA/hq720.jpg","seconds":281,"timestamp":"4:41","duration":{"seconds":281,"timestamp":"4:41"},"ago":"2 years ago","views":274683,"author":{"name":"FayeWongVEVO","url":"https://youtube.com/@FayeWongOfficial"}},{"type":"list","listId":"RDEM6aAI_ldFWJbStUMdcSdgPg","url":"https://youtube.com/playlist?list=RDEM6aAI_ldFWJbStUMdcSdgPg","title":"Mix - Faye Wong","image":"https://i.ytimg.com/vi/5wmfXve11rM/hqdefault.jpg","thumbnail":"https://i.ytimg.com/vi/5wmfXve11rM/hqdefault.jpg","videoCount":"201K subscribers","author":{"name":"Faye Wong, Nana Lee, Julia Peng, and more","url":"https://youtube.com/watch?v=5wmfXve11rM&list=RDEM6aAI_ldFWJbStUMdcSdgPg&start_radio=1"}}],"timestamp":"2026-05-24T21:09:51.898Z"}